Workbook

Sheet Tracker
A1: HOLY CROSS COLLEGE STA. ROSA, N.E., INC. — CHED 3-YEAR TRIMESTER APPLICATION — PROGRESS TRACKER
A2: Requirements taken from the Preliminary Requirement checklist held by the Office of Academic Affairs. Target filing with CHED Region III: 13 November 2026 (Council Resolution 2026-08-03). Yellow cells are for you to update: Status, % and Notes.
A4: # | B4: Requirement | C4: CHED reference | D4: Owner | E4: Support | F4: Due date | G4: Status | H4: % | I4: Notes
A5: AREA A — GOVERNANCE & SUBMISSION
A6: 1 | B6: Transmittal letter to CHED, with copy of the Council of Program Chairs Minutes approving the offering of the new program | C6: Checklist item 1 | D6: MIS Head Jayson R. Francisco | E6: Vice Dean Ken Gie Anthony G. Cruel (drafted both documents); VPAA Sta. Ines (signatory) | F6: 46277 | G6: For review | H6: 1 | I6: Transmittal letter accomplished and Minutes of the 27 Aug 2026 special meeting drafted by the Vice Dean, routed for signing (Res. 2026-08-01, -02, -03). Ownership transferred to the MIS Head on 3 Sep 2026 by direction of the Vice Dean. SIGNATORY CHECK: the CHED Region III Citizen's Charter requires the application letter to be signed by the Chairman of the Board of Trustees or the President, or an authorised representative — not by the VPAA. Confirm who signs before the letter is finalised.
A7: 2 | B7: CHED Program Evaluation — self-evaluation compilation against each programme's CHED Policies, Standards and Guidelines (PSG) | C7: Checklist item 2 | D7: Vice Dean Ken Gie Anthony G. Cruel | E7: All 8 Program Chairs (one PSG comparison each) | F7: 46318 | G7: In progress | H7: 0.5 | I7: RESOLVED 3 Sep 2026: there is no prescribed CHED form. It is a compilation the college prepares against each programme's PSG. Corroborated by the CHED Region III Citizen's Charter, which requires a duly accomplished self-evaluation form per programme on submission. Each of the 8 Chairs supplies their own programme's PSG comparison; the Vice Dean consolidates. 21 Sep 2026: BSA and BSAIS self-evaluations (Official and generated copies) now use the "First Year - Trimester 1" naming convention; the builder was updated to write it. 13 Oct 2026: BSA and BSAIS drafts regenerated as v1.1 (curricular finding complete; 40 programme-outcome mappings and the Year 1 teaching-load rows filled). 11 of 17 institutional requirements per programme still outstanding: faculty roster, library, facilities, internship, admission and retention, and the Sec. 20, 22 and 23 systems. 26 Oct 2026: the BSA and BSAIS Year 1 course syllabi that the self-evaluation cites are now drafted (see item 20 and 26).
A8: AREA B — INSTITUTIONAL FEASIBILITY (Feasibility study for trimestral calendar)
A9: 3 | B9: Philosophy and goals of the program | C9: Checklist item 3.1 | D9: Vice Dean Ken Gie Anthony G. Cruel | E9: VPAA Sta. Ines | F9: 46295 | G9: In progress | H9: 0.5 | I9: 23 Sep 2026: the description and goals of each programme are drafted in Section I of the BSA and BSAIS feasibility studies (BSA & BSAIS Outputs/Feasibility Study). The remaining six programmes still need theirs. 26 Oct 2026: v2 drafts of the BSA and BSAIS feasibility studies now replace the earlier versions (acceptability survey results added; Table 9 mean to be corrected at source).
A10: 4 | B10: Viability — demand for the graduates | C10: Checklist item 3.2.1 | D10: MIS Head Jayson R. Francisco | E10: All Program Chairs; Feasibility & Market Study Committee — full-time faculty, one per department | F10: 46304 | G10: Not started | H10: 0 | I10: Phase 2 of the project plan assigns market demand data gathering to MIS with the Chairs. 23 Sep 2026: Section III of the BSA and BSAIS feasibility studies carries the College's rationale on demand, flagged in the document itself as rationale and not survey findings. The market demand study supersedes it when available. Evidence now in Section III of both studies: 95% of BSA and BSAIS graduates are gainfully employed in work related to their field, on the College's own graduate survey; the first batch of CPALE examinees returned 4 passers out of 6. The survey instrument, period, population and respondents, and the PRC report of rating, must be attached as annexes. 23 Sep 2026: an acceptability survey on the proposed change is ready to run — questionnaire (form ref. HCC-VD-TRI-ACC-01, 23 Likert items in four parts plus preference and open questions) and a tabulation workbook that computes weighted means, verbal interpretations and an acceptability index as responses are encoded. In BSA & BSAIS Outputs/Acceptability Survey. Still to decide: who is asked and how they are chosen — CHED will ask. 23 Sep 2026: house standard set for this application — every document is built on the College's official letterhead template (HEADER-PORTRAIT-SHORT-LONG.docx) on short bond, 8.5 x 11. The feasibility studies and the acceptability survey are already on it. The sampling plan for the survey is in the tabulation workbook: whole-population for the small groups, Slovin at a 5% margin for the large ones. 26 Oct 2026: the Graduate Tracer Study for the Batch of May 2025 is in and replaces the earlier 95% figure. Thirty graduates, twenty-eight employed in work related to their field — 93% overall, BSA 19 of 20 (95%), BSAIS 9 of 10 (90%). Ten were hired within a month of graduating and fifteen within three months; all within eight. One entry marked not employed was confirmed employed by the Vice Dean. Both feasibility studies now carry these figures and the workbook is filed with them.
A11: 5 | B11: Viability — prospective students | C11: Checklist item 3.2.2 | D11: MIS Head Jayson R. Francisco | E11: Registrar Laila D. Sarmiento; Feasibility & Market Study Committee — full-time faculty, one per department | F11: 46304 | G11: Not started | H11: 0 | I11: 23 Sep 2026: the feasibility studies project first-year intake at 30 (BSA) and 25 (BSAIS) growing ten per cent a year, and ask the Registrar for six years of historical freshmen enrolment to confirm or revise it. The 93% employment result from the May 2025 tracer study (BSA 95%) strengthens the prospective-student case and is cited in Section III of both studies. 23 Sep 2026: an acceptability survey on the proposed change is ready to run — questionnaire (form ref. HCC-VD-TRI-ACC-01, 23 Likert items in four parts plus preference and open questions) and a tabulation workbook that computes weighted means, verbal interpretations and an acceptability index as responses are encoded. In BSA & BSAIS Outputs/Acceptability Survey. Still to decide: who is asked and how they are chosen — CHED will ask.
A12: 6 | B12: Viability — existing schools offering the same program within the area | C12: Checklist item 3.2.3 | D12: MIS Head Jayson R. Francisco | E12: All Program Chairs; Feasibility & Market Study Committee — full-time faculty, one per department | F12: 46304 | G12: Not started | H12: 0 | I12: 23 Sep 2026: the feasibility studies state that no other institution in the immediate area offers these programmes on a trimester calendar. This needs the competing-schools study behind it.
A13: 7 | B13: Location of the school in relation to factors that are not conducive to learning | C13: Checklist item 3.3 | D13: VPAA / VP Admin & Finance Dr. Raquel T. Sta. Ines | E13: MIS Head Jayson R. Francisco | F13: 46304 | G13: Not started | H13: 0 | I13: The VPAA also serves as VP for Administration and Finance, so this sits with her office. 23 Sep 2026: the location narrative (Central Luzon, Maharlika Highway, Clark Economic Zone, the Bulacan airport terminal) is drafted in Section III of both feasibility studies.
A14: 8 | B14: Schedule of tuition and other fees (trimestral) | C14: Checklist item 3.4 | D14: Finance Officer Dana Marcelo | E14: Vice Dean Ken Gie Anthony G. Cruel | F14: 46318 | G14: Not started | H14: 0 | I14: Phase 1 of the project plan calls for the trimestral fee distribution model to be initiated. 23 Sep 2026: a computation workbook is ready for the Finance Office — “BSA/BSAIS 3-Year Trimester — Tuition Computation.xlsx”. Enter the rate per unit, the miscellaneous fee per term, the expense ratios and the tax rate, and tuition, collections, expenses and net income compute for five years. Two decisions are still Finance's: the rates themselves, and whether miscellaneous fees are charged at the same amount per term under a three-term year or annualised across three terms.
A15: AREA C — ADMINISTRATORS, FACULTY & NON-TEACHING PERSONNEL
A16: 9 | B16: School administrator spreadsheet — name, educational qualifications (where and when obtained), position/designation, nature of appointment, status, rate of monthly salary, other benefits | C16: Checklist item 4.1 | D16: HR Officer Ellarein Richelle Dela Cruz | E16: Vice Dean Ken Gie Anthony G. Cruel | F16: 46318 | G16: Not started | H16: 0
A17: 10 | B17: School administrator — certified true copy of Transcript of Records, and appointment / notarized contract of employment / letter of commitment with confirmation | C17: Checklist item 4.2 | D17: HR Officer Ellarein Richelle Dela Cruz | E17: VPAA / VP Admin & Finance Dr. Raquel T. Sta. Ines | F17: 46325 | G17: Not started | H17: 0
A18: 11 | B18: Faculty spreadsheet (general education and major courses) — name, educational qualifications, field of specialization, course assignment, nature of appointment, status, rate of monthly salary, other benefits | C18: Checklist item 5.1 | D18: HR Officer Ellarein Richelle Dela Cruz | E18: All 8 Program Chairs (specialization and course assignment) | F18: 46318 | G18: Not started | H18: 0 | I18: Phase 1 of the project plan has HR issuing the call-out for faculty certified true copy Transcripts of Record. 21 Sep 2026: BSA and BSAIS course assignments for First Year - Trimester 1 to 3 are available from the Proposed Faculty Loading (BSA & BSAIS Outputs/Faculty Matrix & Loading).
A19: 12 | B19: Faculty — certified true copies of Transcripts of Record | C19: Checklist item 5.2 | D19: HR Officer Ellarein Richelle Dela Cruz | E19: All 8 Program Chairs | F19: 46325 | G19: Not started | H19: 0
A20: 13 | B20: Faculty — appointment / notarized contract of employment / letter of commitment with confirmation | C20: Checklist item 5.3 | D20: HR Officer Ellarein Richelle Dela Cruz | E20: VPAA Sta. Ines | F20: 46325 | G20: Not started | H20: 0
A21: 14 | B21: List of non-teaching personnel | C21: Checklist item 6 | D21: VPAA / VP Admin & Finance Dr. Raquel T. Sta. Ines | E21: HR Officer Ellarein Richelle Dela Cruz | F21: 46318 | G21: Not started | H21: 0 | I21: Checklist assigns this to Admin. There is no separate Admin Office Head — the VPAA holds the VP for Administration and Finance portfolio.
A22: AREA D — CURRICULUM (per program)
A23: 15 | B23: Curriculum — distribution of courses per trimester (9-term prospectus), BSA | C23: Checklist item 7.1 | D23: Vice Dean Ken Gie Anthony G. Cruel | E23: Vice Dean Ken Gie Anthony G. Cruel (compliance audit); MIS Head Jayson R. Francisco (repository) | F23: 46290 | G23: For review | H23: 1 | I23: Draft 9-trimester prospectus prepared by the Vice Dean — 191 total units across 9 terms. Must be recast onto the agreed template (see Reference): Course Code, Course Title, Lec Hrs, Lab Hrs, Total Hrs, Credit Units, Prerequisite(s), with a sub-total per trimester and the programme's own PSG cited in the header. TERM LENGTH DECIDED, 9 Sep 2026: 14 weeks per trimester, by the Council of Programme Chairs. The contact-hour standard moves with it from 54 to 56 hours per 3-unit subject, so a 3-unit subject runs 240 minutes a week and divides into whole periods (2 x 120, 3 x 80 or 4 x 60 minutes). MEETING DATE AND RESOLUTION NUMBER STILL TO BE SUPPLIED for the dossier. 21 Sep 2026: term headings renamed to the college convention "First Year - Trimester 1", "First Year - Trimester 2" … "Third Year - Trimester 3"; prerequisites now read "Completed Second Year" / "Completed Third Year - Trimester 1".
A24: 16 | B24: Curriculum — summary of units, BSA | C24: Checklist item 7.2 | D24: Vice Dean Ken Gie Anthony G. Cruel | E24: Vice Dean Ken Gie Anthony G. Cruel (compliance audit); MIS Head Jayson R. Francisco (repository) | F24: 46295 | G24: For review | H24: 1 | I24: Unit summary computed in the draft: Yr1 67, Yr2 67, Yr3 57. Two term totals still carry unresolved formulas — verify before finalising. TERM LENGTH DECIDED, 9 Sep 2026: 14 weeks per trimester, by the Council of Programme Chairs. The contact-hour standard moves with it from 54 to 56 hours per 3-unit subject, so a 3-unit subject runs 240 minutes a week and divides into whole periods (2 x 120, 3 x 80 or 4 x 60 minutes). MEETING DATE AND RESOLUTION NUMBER STILL TO BE SUPPLIED for the dossier.
A25: 17 | B25: Updated trimester curriculum — list of subjects with GE and Specialized identified, BSA | C25: Checklist item 9.1 | D25: Vice Dean Ken Gie Anthony G. Cruel | E25: Vice Dean Ken Gie Anthony G. Cruel (compliance audit); MIS Head Jayson R. Francisco (repository) | F25: 46295 | G25: For review | H25: 1 | I25: General education courses are identifiable by code in the draft prospectus; the formal GE versus Specialised tagging sheet is still to be produced.
A26: 18 | B26: Updated trimester curriculum — sample schedule (Trimesters 1, 2 and 3), BSA | C26: Checklist item 9.2 | D26: Vice Dean Ken Gie Anthony G. Cruel | E26: Vice Dean Ken Gie Anthony G. Cruel (compliance audit); MIS Head Jayson R. Francisco (repository) | F26: 46304 | G26: For review | H26: 1 | I26: 21 Sep 2026: PROPOSED SCHEDULE OF CLASSES built for First Year - Trimester 1, 2 and 3 (BSA and BSAIS share one First Year section, 1-BSA-A / 1-BSAIS-A), with the matching PROPOSED FACULTY LOADING. Each trimester carries 31 contact hours a week and 23 units, Monday to Thursday only; Friday is kept free for consultation, make-up classes and student activities. A 3-unit course meets 4 hours a week (2 x 2-hour meetings, MW or TTH), which gives the settled 56 hours over 14 weeks, examination weeks included. Signatories: prepared by the Program Chair, reviewed by the College Dean, approved by the VPAA. Files: BSA & BSAIS Outputs/Sample Schedule/Proposed Schedule of Classes - First Year, Trimesters 1-3 (BSA-BSAIS) and BSA & BSAIS Outputs/Faculty Matrix & Loading/Proposed Faculty Loading - First Year, Trimesters 1-3 (BSA-BSAIS), Word and PDF. NOT YET BUILT: Second Year and Third Year schedules — raise with the Vice Dean if CHED expects all nine trimesters rather than one year's Trimesters 1, 2 and 3. Rooms are provisional (ML 401 for lecture, ML 211 for PATH-FIT).
A27: 19 | B27: Curriculum — course descriptions, BSA | C27: Checklist item 7.3 | D27: Vice Dean Ken Gie Anthony G. Cruel | E27: Vice Dean Ken Gie Anthony G. Cruel (compliance audit); MIS Head Jayson R. Francisco (repository); General Education Syllabi Pool (20 shared GE, PATH-FIT, NSTP and CLE courses, written once for all 8 programs); Business Cluster Pool (shared business, economics and law courses); Course teachers named in the Proposed Faculty Loading, First Year Trimesters 1–3 — J.R. Francisco, CPA; J.R. Empay, CPA; D.N. Santiago, CPA; R. Cruz, CPA (professional courses), each writing the description and syllabus for the courses that loading gives them; M. Germino, N. Tolosa, S.M. Calma, L. Ramos, M. Mequiabas, X. Villamayor, F. Ilag, J. Jamlang (GE, PATH-FIT, NSTP and CLE). Still no full-time faculty besides the Chair — see Open Item 9 | F27: 46304 | G27: For review | H27: 1 | I27: Awaiting the curriculum template. CAPACITY RISK: the programme-specialised courses here have no full-time author other than the Chair.
A28: 20 | B28: Curriculum — course syllabi (outcomes-based), BSA | C28: Checklist item 7.4 | D28: Vice Dean Ken Gie Anthony G. Cruel | E28: Vice Dean Ken Gie Anthony G. Cruel (compliance audit); MIS Head Jayson R. Francisco (repository); General Education Syllabi Pool (20 shared GE, PATH-FIT, NSTP and CLE courses, written once for all 8 programs); Business Cluster Pool (shared business, economics and law courses); Course teachers named in the Proposed Faculty Loading, First Year Trimesters 1–3 — J.R. Francisco, CPA; J.R. Empay, CPA; D.N. Santiago, CPA; R. Cruz, CPA (professional courses), each writing the description and syllabus for the courses that loading gives them; M. Germino, N. Tolosa, S.M. Calma, L. Ramos, M. Mequiabas, X. Villamayor, F. Ilag, J. Jamlang (GE, PATH-FIT, NSTP and CLE). Still no full-time faculty besides the Chair — see Open Item 9 | F28: 46311 | G28: For review | H28: 1 | I28: ASSESSMENT SCHEME confirmed by the Vice Dean, 3 Sep 2026: two examinations per term (midterm and final), one required monthly assessment, plus regular quizzes and activities. Every syllabus must carry this scheme. CAPACITY RISK: the programme-specialised courses here have no full-time author other than the Chair. 26 Oct 2026: all BSA course syllabi drafted on the OBE template (14-week / 56-hour basis, midterm Week 7, final Week 14) in BSA & BSAIS Outputs/Sample Syllabus/Drafts for Review; references left blank; subject-expert review pending. AE7-INT 400-hour deployment still to be confirmed. 26 Oct 2026: the syllabus drafts now carry the course teacher. Prepared by / Subject Instructor on each of the 24 First Year courses is the faculty member the Proposed Faculty Loading assigns to it — 20 changed from the Vice Dean, 4 were already right. Reviewed by (Chair), Recommended by (Vice Dean) and Approved by (Dean) are unchanged. The 51 Second and Third Year syllabi still read Vice Dean as instructor, because no loading has been drawn for those years yet.
A29: 21 | B29: Curriculum — distribution of courses per trimester (9-term prospectus), BSAIS | C29: Checklist item 7.1 | D29: Vice Dean Ken Gie Anthony G. Cruel | E29: Vice Dean Ken Gie Anthony G. Cruel (compliance audit); MIS Head Jayson R. Francisco (repository) | F29: 46290 | G29: For review | H29: 1 | I29: Draft 9-trimester prospectus prepared by the Vice Dean — 185 total units across 9 terms. Must be recast onto the agreed template (see Reference): Course Code, Course Title, Lec Hrs, Lab Hrs, Total Hrs, Credit Units, Prerequisite(s), with a sub-total per trimester and the programme's own PSG cited in the header. TERM LENGTH DECIDED, 9 Sep 2026: 14 weeks per trimester, by the Council of Programme Chairs. The contact-hour standard moves with it from 54 to 56 hours per 3-unit subject, so a 3-unit subject runs 240 minutes a week and divides into whole periods (2 x 120, 3 x 80 or 4 x 60 minutes). MEETING DATE AND RESOLUTION NUMBER STILL TO BE SUPPLIED for the dossier. 21 Sep 2026: term headings renamed to the college convention "First Year - Trimester 1", "First Year - Trimester 2" … "Third Year - Trimester 3"; prerequisites now read "Completed Second Year" / "Completed Third Year - Trimester 1".
A30: 22 | B30: Curriculum — summary of units, BSAIS | C30: Checklist item 7.2 | D30: Vice Dean Ken Gie Anthony G. Cruel | E30: Vice Dean Ken Gie Anthony G. Cruel (compliance audit); MIS Head Jayson R. Francisco (repository) | F30: 46295 | G30: For review | H30: 1 | I30: Unit summary computed in the draft: Yr1 67, Yr2 67, Yr3 51. Two term totals still carry unresolved formulas — verify before finalising. TERM LENGTH DECIDED, 9 Sep 2026: 14 weeks per trimester, by the Council of Programme Chairs. The contact-hour standard moves with it from 54 to 56 hours per 3-unit subject, so a 3-unit subject runs 240 minutes a week and divides into whole periods (2 x 120, 3 x 80 or 4 x 60 minutes). MEETING DATE AND RESOLUTION NUMBER STILL TO BE SUPPLIED for the dossier.
A31: 23 | B31: Updated trimester curriculum — list of subjects with GE and Specialized identified, BSAIS | C31: Checklist item 9.1 | D31: Vice Dean Ken Gie Anthony G. Cruel | E31: Vice Dean Ken Gie Anthony G. Cruel (compliance audit); MIS Head Jayson R. Francisco (repository) | F31: 46295 | G31: For review | H31: 1 | I31: General education courses are identifiable by code in the draft prospectus; the formal GE versus Specialised tagging sheet is still to be produced.
A32: 24 | B32: Updated trimester curriculum — sample schedule (Trimesters 1, 2 and 3), BSAIS | C32: Checklist item 9.2 | D32: Vice Dean Ken Gie Anthony G. Cruel | E32: Vice Dean Ken Gie Anthony G. Cruel (compliance audit); MIS Head Jayson R. Francisco (repository) | F32: 46304 | G32: For review | H32: 1 | I32: 21 Sep 2026: PROPOSED SCHEDULE OF CLASSES built for First Year - Trimester 1, 2 and 3 (BSA and BSAIS share one First Year section, 1-BSA-A / 1-BSAIS-A), with the matching PROPOSED FACULTY LOADING. Each trimester carries 31 contact hours a week and 23 units, Monday to Thursday only; Friday is kept free for consultation, make-up classes and student activities. A 3-unit course meets 4 hours a week (2 x 2-hour meetings, MW or TTH), which gives the settled 56 hours over 14 weeks, examination weeks included. Signatories: prepared by the Program Chair, reviewed by the College Dean, approved by the VPAA. Files: BSA & BSAIS Outputs/Sample Schedule/Proposed Schedule of Classes - First Year, Trimesters 1-3 (BSA-BSAIS) and BSA & BSAIS Outputs/Faculty Matrix & Loading/Proposed Faculty Loading - First Year, Trimesters 1-3 (BSA-BSAIS), Word and PDF. NOT YET BUILT: Second Year and Third Year schedules — raise with the Vice Dean if CHED expects all nine trimesters rather than one year's Trimesters 1, 2 and 3. Rooms are provisional (ML 401 for lecture, ML 211 for PATH-FIT).
A33: 25 | B33: Curriculum — course descriptions, BSAIS | C33: Checklist item 7.3 | D33: Vice Dean Ken Gie Anthony G. Cruel | E33: Vice Dean Ken Gie Anthony G. Cruel (compliance audit); MIS Head Jayson R. Francisco (repository); General Education Syllabi Pool (20 shared GE, PATH-FIT, NSTP and CLE courses, written once for all 8 programs); Business Cluster Pool (shared business, economics and law courses); Course teachers named in the Proposed Faculty Loading, First Year Trimesters 1–3 — J.R. Francisco, CPA; J.R. Empay, CPA; D.N. Santiago, CPA; R. Cruz, CPA (professional courses), each writing the description and syllabus for the courses that loading gives them; M. Germino, N. Tolosa, S.M. Calma, L. Ramos, M. Mequiabas, X. Villamayor, F. Ilag, J. Jamlang (GE, PATH-FIT, NSTP and CLE). Still no full-time faculty besides the Chair — see Open Item 9 | F33: 46304 | G33: For review | H33: 1 | I33: Awaiting the curriculum template. CAPACITY RISK: the programme-specialised courses here have no full-time author other than the Chair.
A34: 26 | B34: Curriculum — course syllabi (outcomes-based), BSAIS | C34: Checklist item 7.4 | D34: Vice Dean Ken Gie Anthony G. Cruel | E34: Vice Dean Ken Gie Anthony G. Cruel (compliance audit); MIS Head Jayson R. Francisco (repository); General Education Syllabi Pool (20 shared GE, PATH-FIT, NSTP and CLE courses, written once for all 8 programs); Business Cluster Pool (shared business, economics and law courses); Course teachers named in the Proposed Faculty Loading, First Year Trimesters 1–3 — J.R. Francisco, CPA; J.R. Empay, CPA; D.N. Santiago, CPA; R. Cruz, CPA (professional courses), each writing the description and syllabus for the courses that loading gives them; M. Germino, N. Tolosa, S.M. Calma, L. Ramos, M. Mequiabas, X. Villamayor, F. Ilag, J. Jamlang (GE, PATH-FIT, NSTP and CLE). Still no full-time faculty besides the Chair — see Open Item 9 | F34: 46311 | G34: For review | H34: 1 | I34: ASSESSMENT SCHEME confirmed by the Vice Dean, 3 Sep 2026: two examinations per term (midterm and final), one required monthly assessment, plus regular quizzes and activities. Every syllabus must carry this scheme. CAPACITY RISK: the programme-specialised courses here have no full-time author other than the Chair. 26 Oct 2026: all BSAIS course syllabi drafted on the OBE template (14-week / 56-hour basis, midterm Week 7, final Week 14) in BSA & BSAIS Outputs/Sample Syllabus/Drafts for Review; references left blank; subject-expert review pending. AE7-INT 400-hour deployment still to be confirmed. 26 Oct 2026: the syllabus drafts now carry the course teacher. Prepared by / Subject Instructor on each of the 24 First Year courses is the faculty member the Proposed Faculty Loading assigns to it — 20 changed from the Vice Dean, 4 were already right. Reviewed by (Chair), Recommended by (Vice Dean) and Approved by (Dean) are unchanged. The 51 Second and Third Year syllabi still read Vice Dean as instructor, because no loading has been drawn for those years yet.
... A70: 62 | B70: Curriculum — course syllabi (outcomes-based), BSED | C70: Checklist item 7.4 | D70: Program Chair Kent E. Garcia | E70: Vice Dean Ken Gie Anthony G. Cruel (compliance audit); MIS Head Jayson R. Francisco (repository); General Education Syllabi Pool (20 shared GE, PATH-FIT, NSTP and CLE courses, written once for all 8 programs); 14 full-time BSED faculty | F70: 46311 | G70: In progress | H70: 0 | I70: ASSESSMENT SCHEME confirmed by the Vice Dean, 3 Sep 2026: two examinations per term (midterm and final), one required monthly assessment, plus regular quizzes and activities. Every syllabus must carry this scheme.
A71: AREA E — LIBRARY
A72: 63 | B72: Librarian — qualification and status per appointment | C72: Checklist item 8.1 | D72: Library Lead Annabelle Pastrana | E72: HR Officer Ellarein Richelle Dela Cruz | F72: 46295 | G72: Not started | H72: 0 | I72: There is no appointed head librarian. Annabelle Pastrana acts as Library Lead in the meantime; Sta. Cruz and Bernardo complete the library team. This item asks for the librarian's qualification and status per appointment, so a designation memo naming Ms. Pastrana as Officer-in-Charge must be issued and attached — the name alone will not close this row.
A73: 64 | B73: List of library facilities | C73: Checklist item 8.2 | D73: Library Lead Annabelle Pastrana | E73: VPAA / VP Admin & Finance Dr. Raquel T. Sta. Ines | F73: 46295 | G73: Not started | H73: 0
A74: 65 | B74: Library seating capacity | C74: Checklist item 8.3 | D74: Library Lead Annabelle Pastrana | E74: VPAA / VP Admin & Finance Dr. Raquel T. Sta. Ines | F74: 46295 | G74: Not started | H74: 0
A75: 66 | B75: Library collections spreadsheet (books, journals, magazines, dictionaries, almanacs) — author, title, year of publication, number of volumes | C75: Checklist item 8.4.1 | D75: Library Lead Annabelle Pastrana | E75: Sta. Cruz (also Teacher Education faculty); Bernardo (also Hospitality Management faculty); Library Collection Committee — full-time faculty, one per department | F75: 46304 | G75: Not started | H75: 0
A76: 67 | B76: List of 5 non-duplicated titles per subject in the curriculum, published within the last 5 years | C76: Checklist item 8.4.2 | D76: Library Lead Annabelle Pastrana | E76: Sta. Cruz; Bernardo; All 8 Program Chairs (subject lists); Library Collection Committee — full-time faculty, one per department | F76: 46311 | G76: Not started | H76: 0 | I76: Project plan reads this as titles published 2021-2026. Depends on the curriculum subject lists (item 9.1) for all 8 programs.
A77: 68 | B77: List of book collections / accessioned books (start-up 3,000 books; recognition 5,000 books) | C77: Checklist item 8.4.3 | D77: Library Lead Annabelle Pastrana | E77: Sta. Cruz (also Teacher Education faculty); Bernardo (also Hospitality Management faculty) | F77: 46311 | G77: Not started | H77: 0 | I77: OPEN ITEM 3 — confirm whether the 3,000 or the 5,000 threshold applies to a trimestral conversion of existing programs.
A78: 69 | B78: List of subscribed journals | C78: Checklist item 8.4.4 | D78: Library Lead Annabelle Pastrana | E78: Sta. Cruz (also Teacher Education faculty); Bernardo (also Hospitality Management faculty) | F78: 46304 | G78: Not started | H78: 0
A79: AREA F — CONSOLIDATION, FILING & INTERNAL COORDINATION (from the internal project plan — not items on the CHED checklist)
A80: 70 | B80: Index, print, digitise and assemble the hard copy and soft copy master application binders | C80: Internal — project plan Phase 3 | D80: MIS Head Jayson R. Francisco | E80: Admin staff; Vice Dean Ken Gie Anthony G. Cruel | F80: 46332 | G80: Not started | H80: 0 | I80: OPEN ITEM 4 — number of binder copies required by CHED Region III not yet confirmed.
A81: 71 | B81: Secure executive endorsement of the completed dossier | C81: Internal — project plan Phase 4 | D81: Vice Dean Ken Gie Anthony G. Cruel | E81: Dean Dr. Almario B. Garcia; VPAA Dr. Raquel T. Sta. Ines | F81: 46336 | G81: Not started | H81: 0
A82: 72 | B82: File the application dossier with CHED Region III and secure the receiving copy | C82: Internal — project plan Phase 4 | D82: Vice Dean Ken Gie Anthony G. Cruel | E82: MIS Head Jayson R. Francisco; administrative staff | F82: 46339 | G82: Not started | H82: 0 | I82: Target submission date set by Council Resolution 2026-08-03.
A83: 73 | B83: Secure written clarification from CHED Region III on the five unresolved requirement questions | C83: Internal — raised by the Vice Dean, 3 Sep 2026 | D83: MIS Head Jayson R. Francisco | E83: Vice Dean Ken Gie Anthony G. Cruel | F83: 46290 | G83: Not started | H83: 0 | I83: Covers Open Items 2 to 5 — the questions only CHED Region III can answer. (Open Item 1, the 14-versus-15-week term length, is for the Council of Chairs, not CHED.) The questions are: which form is meant by 'CHED Program Evaluation'; which issuance governs a shift to trimestral delivery; whether the 3,000 or 5,000 book threshold applies to a conversion of existing programmes; how many hard and soft copies Region III requires; and whether syllabi are needed for every course or only new and re-sequenced ones. The syllabi question is the one that matters most — it drives the 16 October deadline on items 15 to 62, which is why this is dated 25 September.
A84: 74 | B84: General Education Syllabi Pool — publish the writer allocation, the common syllabus template and the internal hand-in dates | C84: Internal — raised by the Vice Dean, 9 Sep 2026 | D84: Program Chair Kent E. Garcia | E84: General Education Syllabi Pool — 7 writers (Ilag, Germino, Calma, Mequiabas, Manuel, Tolosa, Jamlang); Vice Dean Ken Gie Anthony G. Cruel (GE code harmonisation); all 8 Program Chairs (recipients) | F84: 46290 | G84: Not started | H84: 0 | I84: POOL LEAD: Chair Kent E. Garcia (named 9 Sep 2026). ALLOCATION REVISED 13 Sep 2026 by direction of the Vice Dean — all 20 courses are assigned by name across SEVEN writers (Aquino, Agnes M. was moved out of the pool on the same date to write BEED/BSED major courses under item 79 instead). Ilag: REL-GEC, CLE 1, CLE 2, STS-GEC. Germino: HIS-GEC. Calma: PATH-FIT 1, PATH-FIT 2, NSTP 1. Mequiabas: PATH-FIT 3, PATH-FIT 4, NSTP 2. Manuel: ETH-GEC, MAT-GEC, BL-GEC. Tolosa: ART-GEC, COM-GEC, US-GEC. Jamlang: CON-GEC, ITE-GEC, RIZ-GEC — two only, on the heaviest teaching load in the pool at 27 units over 5 preps. Each writer produces the description AND the syllabus per course. THE LEAD'S TASKS: issue one common syllabus template carrying the assessment scheme and the 14-week / 56-hour basis; set internal hand-in dates ahead of 9 Oct and 16 Oct; hand one finished set to all 8 Chairs; report slippage weekly to the Vice Dean. WATCH: NSTP 1 is the prerequisite of NSTP 2 and they now sit with different writers — Calma and Mequiabas must agree the two syllabi between them. STILL BLOCKED BY OPEN ITEM 7 — the GE course codes do not match across programmes, so the allocation is not final until they are harmonised. He convenes and reports; each Programme Chair still answers for their own 7.3 and 7.4 rows. 26 Oct 2026: the Vice Dean has drafted syllabi for all 20 GE, PATH-FIT, NSTP and CLE courses (Drafts for Review) for the writers to adopt, check and finalise. Open Item 7 (code mismatch) still applies. REALLOCATED 26 Oct 2026 — D. Maglalang resigned. Her three courses went to the faculty who teach them in the Proposed Faculty Loading: CLE 2 to Ilag (who already has CLE 1), HIS-GEC to Germino (who teaches it in First Year - Trimester 1, and joins the pool for it), RIZ-GEC to Jamlang (who teaches it in First Year - Trimester 3). Still seven writers.
A85: 75 | B85: Business Cluster Pool — fix the definitive shared-course list and publish the writer allocation and internal hand-in dates | C85: Internal — raised by the Vice Dean, 9 Sep 2026 | D85: Program Chair Ranilo S. Castillo II | E85: Business Cluster Pool (Aquino (Ann Jellie), Bauat, Dela Cruz (Jacqueline), Salas); Vice Dean Ken Gie Anthony G. Cruel; Program Chairs of BSA, BSAIS and BSHM (recipients) | F85: 46290 | G85: Not started | H85: 0 | I85: POOL LEAD NAMED 9 Sep 2026: Chair Ranilo S. Castillo II convenes the Business Cluster Pool. The pool writes the shared business, economics and law courses ONCE for BSA, BSAIS, BSBA and BSHM, so its output feeds items 19-20, 25-26, 31-32 and 43-44. THE LEAD'S SPECIFIC TASKS: (1) FIX THE DEFINITIVE COURSE LIST — it is still recorded only as 'about 12 to 13 courses' and no exact list exists, so this comes first; (2) publish the allocation across the 4 writers; (3) use the same common syllabus template as the GE pool; (4) set internal hand-in dates ahead of 9 Oct and 16 Oct; (5) hand ONE copy to the Chairs of BSA, BSAIS, BSBA and BSHM; (6) report slippage to the Vice Dean. BSA and BSAIS have no full-time faculty of their own, so this pool is the only source of these courses for two of the four programmes. The Chair convenes and reports; each Programme Chair still answers for their own 7.3 and 7.4 rows. 26 Oct 2026: the Vice Dean has drafted syllabi for the business, economics and law courses (Drafts for Review) for the writers to adopt, check and finalise.
A86: 76 | B86: Programme-specialised writer allocation, BSCRIM — publish which full-time faculty writes which BSCRIM major course, with the internal hand-in dates | C86: Internal — raised by the Vice Dean, 13 Sep 2026 | D86: Program Chair Samantha Rose C. Pisto | E86: BSCRIM full-time faculty (Arimbuyutan, Dela Cruz (Jhon Allen), Diaz, Pamiloza, Ramos); Vice Dean Ken Gie Anthony G. Cruel | F86: 46290 | G86: Not started | H86: 0 | I86: Five full-time writers — the best-staffed department in the college after Teacher Education. Until this allocation names their courses, each of the five carries a counted task on the Faculty sheet rather than a named one. Use the common template (14 weeks / 56 hours; two exams plus a monthly assessment). Internal hand-in: descriptions 9 Oct 2026, syllabi 16 Oct 2026. Feeds items 49 and 50. NOTE against item 45: the two 25-unit BSCRIM trimesters put students at 8.33 contact hours a day and are still to be fixed.
A87: 77 | B87: Programme-specialised writer allocation, BSHM — publish which full-time faculty writes which BSHM major course, with the internal hand-in dates | C87: Internal — raised by the Vice Dean, 13 Sep 2026 | D87: Program Chair Stephanie S. Ciasico | E87: BSHM full-time faculty (Bernardo, Dela Cruz (Jonathan), Geronimo); Vice Dean Ken Gie Anthony G. Cruel | F87: 46290 | G87: Not started | H87: 0 | I87: Three full-time writers, and the shared business courses are already covered by the Business Cluster Pool under item 75, so this allocation covers hospitality-specialised courses only. Bernardo also carries library items 66 to 69 on top of a 21-unit load — weight his share accordingly. Internal hand-in: descriptions 9 Oct 2026, syllabi 16 Oct 2026. Feeds items 43 and 44.
A88: 78 | B88: Programme-specialised writer allocation, BSCS — publish which full-time faculty writes which BSCS major course, with the internal hand-in dates | C88: Internal — raised by the Vice Dean, 13 Sep 2026 | D88: Program Chair John Philip N. Diamat | E88: Cristobal, Teofilo G. (the department's only other full-time faculty); Vice Dean Ken Gie Anthony G. Cruel | F88: 46290 | G88: Not started | H88: 0 | I88: CAPACITY WARNING — this department has exactly one full-time writer besides the Chair. Cristobal, Teofilo G. cannot absorb the BSCS major courses alone, so this allocation must state plainly which courses fall to the Chair himself and which, if any, need help from outside the department. The same shape of problem as Open Item 9. Correct Cristobal's department on the roster main sheet (he is BSCS, not Teacher Education) before the dossier is filed. Internal hand-in: descriptions 9 Oct 2026, syllabi 16 Oct 2026. Feeds items 37 and 38.
A89: 79 | B89: Programme-specialised writer allocation, BEED and BSED — publish which full-time faculty writes which education major course, with the internal hand-in dates | C89: Internal — raised by the Vice Dean, 13 Sep 2026 | D89: Program Chair Kent E. Garcia | E89: The seven Teacher Education full-time faculty not in the GE pool (Ablaya, Aquino (Agnes), Cajucom, Delos Reyes, Germino, Sta. Cruz, Villamayor); Vice Dean Ken Gie Anthony G. Cruel | F89: 46290 | G89: Not started | H89: 0 | I89: The seven Teacher Education faculty in the General Education Syllabi Pool are writing 20 courses for the whole college under item 74 and are deliberately EXCLUDED from this allocation. SEVEN writers remain for the BEED and BSED major courses — Aquino, Agnes M. was moved out of the GE pool on 13 Sep 2026 by direction of the Vice Dean and joins this group, on the heaviest prep count in the department at 7. Sta. Cruz also carries library items 66 to 69 on top of a 27-unit load — weight her share accordingly. Internal hand-in: descriptions 9 Oct 2026, syllabi 16 Oct 2026. Feeds items 55 and 56 (BEED) and 61 and 62 (BSED).
A90: 80 | B90: Programme-specialised writer allocation, BSBA — publish which full-time faculty writes which BSBA major course, over and above the shared cluster courses in item 75 | C90: Internal — raised by the Vice Dean, 13 Sep 2026 | D90: Program Chair Ranilo S. Castillo II | E90: BSBA full-time faculty (Aquino (Ann Jellie), Bauat, Dela Cruz (Jacqueline), Salas); Vice Dean Ken Gie Anthony G. Cruel | F90: 46290 | G90: Not started | H90: 0 | I90: DOUBLE LOAD — the same four faculty write the 13 shared business courses under item 75 AND the BSBA major courses here. After the Vice Dean, this is the heaviest concentration of writing on any group in the college, and all four already carry 24 units. Publish both allocations together so the total per writer is visible, and say which courses the Chair takes himself. Internal hand-in: descriptions 9 Oct 2026, syllabi 16 Oct 2026. Feeds items 31 and 32.

Sheet Assignments
A1: ASSIGNMENT MATRIX — WHO OWNS WHAT
A2: Item numbers refer to the # column on the Tracker sheet. Owner means one person is accountable for delivering that document; Support means they must supply input, but the Owner answers for it. Only full-time faculty are tasked — the 21 part-time faculty remain on the Faculty sheet for checklist item 5.1 and carry no project work, but every faculty member, part-time included, must still lodge their own transcript and contract with HR for items 12 and 13. Because BSA, BSAIS and BSCS have no full-time faculty besides their Chair, manpower is borrowed through two college-wide pools. As of 13 September 2026 every full-time faculty member has a named, answerable task: the 12 pool writers are allocated specific courses below, and the other 15 hold a counted task until their Chair publishes the departmental allocation under items 76 to 80, due 25 September 2026.
A4: Person or Office | B4: Role in project | C4: Items owned | D4: Items supporting | E4: Nearest due date
A5: LEADS, OFFICES AND PROGRAM CHAIRS
A6: Vice Dean Ken Gie Anthony G. Cruel | B6: Co-Lead, CHED Application Task Force; Program Chair for BSA and BSAIS; overall compliance audit and filing. Sole full-time author for the programme-specialised accountancy and AIS courses — see Open Item 9 | C6: 16 items: #2–3, 15–26, 71–72 | D6: 53 items: #1, 4, 6, 8–9, 11–12, 27–62, 67, 70, 73–80 | E6: =IF(COUNTIFS(Tracker!$D$5:$D$90,$A6,Tracker!$G$5:$G$90,"<>Done")=0,"—",_xlfn.MINIFS(Tracker!$F$5:$F$90,Tracker!$D$5:$D$90,$A6,Tracker!$G$5:$G$90,"<>Done"))
A7: MIS Head Jayson R. Francisco | B7: Co-Lead, CHED Application Task Force; owner of the transmittal letter and minutes package (item 1, transferred 3 Sep 2026); chairs the Feasibility & Market Study Committee; document repository and binder assembly; carries the outstanding CHED Region III questions (item 73) | C7: 6 items: #1, 4–6, 70, 73 | D7: 50 items: #7, 15–62, 72 | E7: =IF(COUNTIFS(Tracker!$D$5:$D$90,$A7,Tracker!$G$5:$G$90,"<>Done")=0,"—",_xlfn.MINIFS(Tracker!$F$5:$F$90,Tracker!$D$5:$D$90,$A7,Tracker!$G$5:$G$90,"<>Done"))
A8: VPAA / VP Admin & Finance Dr. Raquel T. Sta. Ines | B8: Presiding officer, Council of Program Chairs; signatory and approving authority; also holds the VP for Administration and Finance portfolio, so the non-teaching personnel list and the school location report sit with her office | C8: 2 items: #7, 14 | D8: 7 items: #1, 3, 10, 13, 64–65, 71 | E8: =IF(COUNTIFS(Tracker!$D$5:$D$90,$A8,Tracker!$G$5:$G$90,"<>Done")=0,"—",_xlfn.MINIFS(Tracker!$F$5:$F$90,Tracker!$D$5:$D$90,$A8,Tracker!$G$5:$G$90,"<>Done"))
A9: Dean Dr. Almario B. Garcia | B9: Co-Lead, CHED Application Task Force (added 3 Sep 2026 by direction of the Vice Dean, alongside the Vice Dean and the MIS Head); College Dean; executive endorsement of the completed dossier | C9: None — support role only | D9: 1 item: #71 | E9: =IF(COUNTIFS(Tracker!$D$5:$D$90,$A9,Tracker!$G$5:$G$90,"<>Done")=0,"—",_xlfn.MINIFS(Tracker!$F$5:$F$90,Tracker!$D$5:$D$90,$A9,Tracker!$G$5:$G$90,"<>Done"))
A10: HR Officer Ellarein Richelle Dela Cruz | B10: Owner of all administrator, faculty and personnel records | C10: 5 items: #9–13 | D10: 2 items: #14, 63 | E10: =IF(COUNTIFS(Tracker!$D$5:$D$90,$A10,Tracker!$G$5:$G$90,"<>Done")=0,"—",_xlfn.MINIFS(Tracker!$F$5:$F$90,Tracker!$D$5:$D$90,$A10,Tracker!$G$5:$G$90,"<>Done"))
A11: Library Lead Annabelle Pastrana | B11: Acting Library Lead — owner of the complete library section; chairs the Library Collection Committee | C11: 7 items: #63–69 | D11: — | E11: =IF(COUNTIFS(Tracker!$D$5:$D$90,$A11,Tracker!$G$5:$G$90,"<>Done")=0,"—",_xlfn.MINIFS(Tracker!$F$5:$F$90,Tracker!$D$5:$D$90,$A11,Tracker!$G$5:$G$90,"<>Done"))
A12: Program Chair Kent E. Garcia | B12: Program Chair, Teacher Education — BEED and BSED curriculum; chairs their Curriculum & Syllabi Committee; his department supplies the General Education Syllabi Pool for the whole college; LEAD of the General Education Syllabi Pool (item 74) — allocates the 20 shared courses across its 8 writers, issues the common syllabus template, sets the internal hand-in dates and reports slippage to the Vice Dean | C12: 14 items: #51–62, 74, 79 | D12: 6 items: #2, 4, 6, 11–12, 67 | E12: =IF(COUNTIFS(Tracker!$D$5:$D$90,$A12,Tracker!$G$5:$G$90,"<>Done")=0,"—",_xlfn.MINIFS(Tracker!$F$5:$F$90,Tracker!$D$5:$D$90,$A12,Tracker!$G$5:$G$90,"<>Done"))
A13: Program Chair Ranilo S. Castillo II | B13: Program Chair, Business Administration — BSBA curriculum; his department supplies the Business Cluster Pool for BSA, BSAIS and BSHM; LEAD of the Business Cluster Pool (item 75) — fixes the definitive shared-course list, allocates it across its 4 writers, sets the internal hand-in dates and reports slippage to the Vice Dean | C13: 8 items: #27–32, 75, 80 | D13: 7 items: #2, 4, 6, 11–12, 67, 74 | E13: =IF(COUNTIFS(Tracker!$D$5:$D$90,$A13,Tracker!$G$5:$G$90,"<>Done")=0,"—",_xlfn.MINIFS(Tracker!$F$5:$F$90,Tracker!$D$5:$D$90,$A13,Tracker!$G$5:$G$90,"<>Done"))
A14: Program Chair John Philip N. Diamat | B14: Program Chair, Computer Science — BSCS curriculum. Sole full-time author for the programme-specialised computer science courses — see Open Item 9 | C14: 7 items: #33–38, 78 | D14: 7 items: #2, 4, 6, 11–12, 67, 74 | E14: =IF(COUNTIFS(Tracker!$D$5:$D$90,$A14,Tracker!$G$5:$G$90,"<>Done")=0,"—",_xlfn.MINIFS(Tracker!$F$5:$F$90,Tracker!$D$5:$D$90,$A14,Tracker!$G$5:$G$90,"<>Done"))
A15: Program Chair Stephanie S. Ciasico | B15: Program Chair, Hospitality Management — BSHM curriculum; chairs its Curriculum & Syllabi Committee | C15: 7 items: #39–44, 77 | D15: 8 items: #2, 4, 6, 11–12, 67, 74–75 | E15: =IF(COUNTIFS(Tracker!$D$5:$D$90,$A15,Tracker!$G$5:$G$90,"<>Done")=0,"—",_xlfn.MINIFS(Tracker!$F$5:$F$90,Tracker!$D$5:$D$90,$A15,Tracker!$G$5:$G$90,"<>Done"))
A16: Program Chair Samantha Rose C. Pisto | B16: Program Chair, Criminal Justice Education — BSCRIM curriculum; chairs its Curriculum & Syllabi Committee | C16: 7 items: #45–50, 76 | D16: 7 items: #2, 4, 6, 11–12, 67, 74 | E16: =IF(COUNTIFS(Tracker!$D$5:$D$90,$A16,Tracker!$G$5:$G$90,"<>Done")=0,"—",_xlfn.MINIFS(Tracker!$F$5:$F$90,Tracker!$D$5:$D$90,$A16,Tracker!$G$5:$G$90,"<>Done"))
A17: Finance Officer Dana Marcelo | B17: Trimestral tuition and fee schedule | C17: 1 item: #8 | D17: — | E17: =IF(COUNTIFS(Tracker!$D$5:$D$90,$A17,Tracker!$G$5:$G$90,"<>Done")=0,"—",_xlfn.MINIFS(Tracker!$F$5:$F$90,Tracker!$D$5:$D$90,$A17,Tracker!$G$5:$G$90,"<>Done"))
A18: Registrar Laila D. Sarmiento | B18: Enrolment and prospective-student data for the feasibility study | C18: None — support role only | D18: 1 item: #5 | E18: =IF(COUNTIFS(Tracker!$D$5:$D$90,$A18,Tracker!$G$5:$G$90,"<>Done")=0,"—",_xlfn.MINIFS(Tracker!$F$5:$F$90,Tracker!$D$5:$D$90,$A18,Tracker!$G$5:$G$90,"<>Done"))
A19: ACCOUNTANCY & AIS — Curriculum & Syllabi Committee for BSA and BSAIS (chaired by Vice Dean Cruel) (NO full-time faculty besides the Chair; 5 part-time not tasked)
A20: Francisco, Josephine Rose, CPA | B20: Named in the Proposed Faculty Loading, First Year Trimesters 1–3 — teaches AE13-FAR Financial Accounting and Reporting (T1), AE14-CFAS Conceptual Framework and Accounting Standards (T2). Writes the course description and outcomes-based syllabus for those courses. | C20: None — support role only | D20: 4 items: #19–20, 25–26 | E20: —
A21: Empay, Jan Rhommer, CPA | B21: Named in the Proposed Faculty Loading, First Year Trimesters 1–3 — teaches CBME 1 Operations Management and TQM (T1), AE1-BL1 Law on Obligations and Contracts (T3). Writes the course description and outcomes-based syllabus for those courses. | C21: None — support role only | D21: 4 items: #19–20, 25–26
A22: Santiago, Decirae Nicole, CPA | B22: Named in the Proposed Faculty Loading, First Year Trimesters 1–3 — teaches AE4-MGT1 Management Science (T3). Writes the course description and outcomes-based syllabus for those courses. | C22: None — support role only | D22: 4 items: #19–20, 25–26
A23: Cruz, Rommel, CPA | B23: Named in the Proposed Faculty Loading, First Year Trimesters 1–3 — teaches AE19-FINMGT Financial Management (T3). Writes the course description and outcomes-based syllabus for those courses. | C23: None — support role only | D23: 4 items: #19–20, 25–26
A24: — still no full-time faculty besides the Chair — | B24: The four above are part-time. The General Education, PE, NSTP and CLE courses of the First Year loading are written by the pool writers listed under Teacher Education and Criminal Justice Education. The Article VI full-time faculty requirement is still open — see Open Item 9. | C24: — | D24: —
A25: BUSINESS ADMINISTRATION — Curriculum & Syllabi Committee for BSBA (chaired by Chair Castillo) (4 full-time faculty tasked; 1 part-time not tasked)
A26: Aquino, Ann Jellie B. | B26: Business Cluster Pool writer (item 75) — writes the course description AND the OBE syllabus for 3 courses: AE11-ECO1 Managerial Economics; AE12-ECO2 Economic Development; AE5-IBT International Business and Trade. 6 documents, one set serving BSA, BSAIS, BSBA and BSHM. Candidate list, to be confirmed by Chair Castillo against the BSBA and BSHM prospectuses. To Chair Castillo: descriptions 9 Oct, syllabi 16 Oct 2026. Also Curriculum & Syllabi — BSBA, and a share of the BSBA major courses under item 80. [FT, 24 units, 6 preps this semester] | C26: None — support role only | D26: 13 items: #4–6, 19–20, 25–26, 31–32, 43–44, 75, 80 | E26: =IF(MIN(IF(Tracker!$G$10="Done",99999,Tracker!$F$10),IF(Tracker!$G$11="Done",99999,Tracker!$F$11),IF(Tracker!$G$12="Done",99999,Tracker!$F$12),IF(Tracker!$G$27="Done",99999,Tracker!$F$27),IF(Tracker!$G$28="Done",99999,Tracker!$F$28),IF(Tracker!$G$33="Done",99999,Tracker!$F$33),IF(Tracker!$G$34="Done",99999,Tracker!$F$34),IF(Tracker!$G$39="Done",99999,Tracker!$F$39),IF(Tracker!$G$40="Done",99999,Tracker!$F$40),IF(Tracker!$G$51="Done",99999,Tracker!$F$51),IF(Tracker!$G$52="Done",99999,Tracker!$F$52))=99999,"—",MIN(IF(Tracker!$G$10="Done",99999,Tracker!$F$10),IF(Tracker!$G$11="Done",99999,Tracker!$F$11),IF(Tracker!$G$12="Done",99999,Tracker!$F$12),IF(Tracker!$G$27="Done",99999,Tracker!$F$27),IF(Tracker!$G$28="Done",99999,Tracker!$F$28),IF(Tracker!$G$33="Done",99999,Tracker!$F$33),IF(Tracker!$G$34="Done",99999,Tracker!$F$34),IF(Tracker!$G$39="Done",99999,Tracker!$F$39),IF(Tracker!$G$40="Done",99999,Tracker!$F$40),IF(Tracker!$G$51="Done",99999,Tracker!$F$51),IF(Tracker!$G$52="Done",99999,Tracker!$F$52)))
A27: Bauat, Jhosalyn | B27: Business Cluster Pool writer (item 75) — writes the course description AND the OBE syllabus for 4 courses: CBME 1 Operations Management and TQM; CBME 2 Strategic Management; AE4-MGT1 Management Science; PE1-HBO Human Behavior in Organizations. 8 documents, one set serving BSA, BSAIS, BSBA and BSHM. Candidate list, to be confirmed by Chair Castillo against the BSBA and BSHM prospectuses. To Chair Castillo: descriptions 9 Oct, syllabi 16 Oct 2026. Also Curriculum & Syllabi — BSBA, and a share of the BSBA major courses under item 80. [FT, 24 units, 6 preps this semester] | C27: None — support role only | D27: 10 items: #19–20, 25–26, 31–32, 43–44, 75, 80 | E27: =IF(MIN(IF(Tracker!$G$27="Done",99999,Tracker!$F$27),IF(Tracker!$G$28="Done",99999,Tracker!$F$28),IF(Tracker!$G$33="Done",99999,Tracker!$F$33),IF(Tracker!$G$34="Done",99999,Tracker!$F$34),IF(Tracker!$G$39="Done",99999,Tracker!$F$39),IF(Tracker!$G$40="Done",99999,Tracker!$F$40),IF(Tracker!$G$51="Done",99999,Tracker!$F$51),IF(Tracker!$G$52="Done",99999,Tracker!$F$52))=99999,"—",MIN(IF(Tracker!$G$27="Done",99999,Tracker!$F$27),IF(Tracker!$G$28="Done",99999,Tracker!$F$28),IF(Tracker!$G$33="Done",99999,Tracker!$F$33),IF(Tracker!$G$34="Done",99999,Tracker!$F$34),IF(Tracker!$G$39="Done",99999,Tracker!$F$39),IF(Tracker!$G$40="Done",99999,Tracker!$F$40),IF(Tracker!$G$51="Done",99999,Tracker!$F$51),IF(Tracker!$G$52="Done",99999,Tracker!$F$52)))
A28: Dela Cruz, Jacqueline | B28: Business Cluster Pool writer (item 75) — writes the course description AND the OBE syllabus for 3 courses: AE19-FINMGT Financial Management; AE18-FINMKT Financial Markets; AE10-GOV Governance, Business Ethics, Risk Management and Internal Control. 6 documents, one set serving BSA, BSAIS, BSBA and BSHM. Candidate list, to be confirmed by Chair Castillo against the BSBA and BSHM prospectuses. To Chair Castillo: descriptions 9 Oct, syllabi 16 Oct 2026. Also Curriculum & Syllabi — BSBA, and a share of the BSBA major courses under item 80. [FT, 24 units, 5 preps this semester] | C28: None — support role only | D28: 12 items: #19–20, 25–26, 31–32, 43–44, 66–67, 75, 80 | E28: =IF(MIN(IF(Tracker!$G$27="Done",99999,Tracker!$F$27),IF(Tracker!$G$28="Done",99999,Tracker!$F$28),IF(Tracker!$G$33="Done",99999,Tracker!$F$33),IF(Tracker!$G$34="Done",99999,Tracker!$F$34),IF(Tracker!$G$39="Done",99999,Tracker!$F$39),IF(Tracker!$G$40="Done",99999,Tracker!$F$40),IF(Tracker!$G$51="Done",99999,Tracker!$F$51),IF(Tracker!$G$52="Done",99999,Tracker!$F$52),IF(Tracker!$G$75="Done",99999,Tracker!$F$75),IF(Tracker!$G$76="Done",99999,Tracker!$F$76))=99999,"—",MIN(IF(Tracker!$G$27="Done",99999,Tracker!$F$27),IF(Tracker!$G$28="Done",99999,Tracker!$F$28),IF(Tracker!$G$33="Done",99999,Tracker!$F$33),IF(Tracker!$G$34="Done",99999,Tracker!$F$34),IF(Tracker!$G$39="Done",99999,Tracker!$F$39),IF(Tracker!$G$40="Done",99999,Tracker!$F$40),IF(Tracker!$G$51="Done",99999,Tracker!$F$51),IF(Tracker!$G$52="Done",99999,Tracker!$F$52),IF(Tracker!$G$75="Done",99999,Tracker!$F$75),IF(Tracker!$G$76="Done",99999,Tracker!$F$76)))
A29: Salas, Kristine Joy | B29: Business Cluster Pool writer (item 75) — writes the course description AND the OBE syllabus for 3 courses: AE1-BL1 Law on Obligations and Contracts; AE2-BL2 Business Laws and Regulations; AE3-BL3 Regulatory Framework and Legal Issues in Business. 6 documents, one set serving BSA, BSAIS, BSBA and BSHM. Candidate list, to be confirmed by Chair Castillo against the BSBA and BSHM prospectuses. To Chair Castillo: descriptions 9 Oct, syllabi 16 Oct 2026. Also Curriculum & Syllabi — BSBA, and a share of the BSBA major courses under item 80. [FT, 24 units, 6 preps this semester] | C29: None — support role only | D29: 10 items: #19–20, 25–26, 31–32, 43–44, 75, 80 | E29: =IF(MIN(IF(Tracker!$G$27="Done",99999,Tracker!$F$27),IF(Tracker!$G$28="Done",99999,Tracker!$F$28),IF(Tracker!$G$33="Done",99999,Tracker!$F$33),IF(Tracker!$G$34="Done",99999,Tracker!$F$34),IF(Tracker!$G$39="Done",99999,Tracker!$F$39),IF(Tracker!$G$40="Done",99999,Tracker!$F$40),IF(Tracker!$G$51="Done",99999,Tracker!$F$51),IF(Tracker!$G$52="Done",99999,Tracker!$F$52))=99999,"—",MIN(IF(Tracker!$G$27="Done",99999,Tracker!$F$27),IF(Tracker!$G$28="Done",99999,Tracker!$F$28),IF(Tracker!$G$33="Done",99999,Tracker!$F$33),IF(Tracker!$G$34="Done",99999,Tracker!$F$34),IF(Tracker!$G$39="Done",99999,Tracker!$F$39),IF(Tracker!$G$40="Done",99999,Tracker!$F$40),IF(Tracker!$G$51="Done",99999,Tracker!$F$51),IF(Tracker!$G$52="Done",99999,Tracker!$F$52)))
A30: CRIMINAL JUSTICE EDUCATION — Curriculum & Syllabi Committee for BSCRIM (chaired by Chair Pisto) (5 full-time faculty tasked; 1 part-time not tasked)
A31: Arimbuyutan, Jazzele M. | B31: Curriculum & Syllabi — BSCRIM; Feasibility & Market Study [FT, 21 units, 4 preps this semester] | C31: None — support role only | D31: 6 items: #4–6, 49–50, 76 | E31: =IF(MIN(IF(Tracker!$G$10="Done",99999,Tracker!$F$10),IF(Tracker!$G$11="Done",99999,Tracker!$F$11),IF(Tracker!$G$12="Done",99999,Tracker!$F$12),IF(Tracker!$G$57="Done",99999,Tracker!$F$57),IF(Tracker!$G$58="Done",99999,Tracker!$F$58))=99999,"—",MIN(IF(Tracker!$G$10="Done",99999,Tracker!$F$10),IF(Tracker!$G$11="Done",99999,Tracker!$F$11),IF(Tracker!$G$12="Done",99999,Tracker!$F$12),IF(Tracker!$G$57="Done",99999,Tracker!$F$57),IF(Tracker!$G$58="Done",99999,Tracker!$F$58)))
A32: Dela Cruz, Jhon Allen R. | B32: Curriculum & Syllabi — BSCRIM [FT, 22 units, 5 preps this semester] | C32: None — support role only | D32: 3 items: #49–50, 76 | E32: =IF(MIN(IF(Tracker!$G$57="Done",99999,Tracker!$F$57),IF(Tracker!$G$58="Done",99999,Tracker!$F$58))=99999,"—",MIN(IF(Tracker!$G$57="Done",99999,Tracker!$F$57),IF(Tracker!$G$58="Done",99999,Tracker!$F$58)))
A33: Diaz, Pamela B. | B33: Curriculum & Syllabi — BSCRIM [FT, 22 units, 5 preps this semester] | C33: None — support role only | D33: 3 items: #49–50, 76 | E33: =IF(MIN(IF(Tracker!$G$57="Done",99999,Tracker!$F$57),IF(Tracker!$G$58="Done",99999,Tracker!$F$58))=99999,"—",MIN(IF(Tracker!$G$57="Done",99999,Tracker!$F$57),IF(Tracker!$G$58="Done",99999,Tracker!$F$58)))
A34: Pamiloza, Honey Mica R. | B34: Curriculum & Syllabi — BSCRIM [FT, 21 units, 4 preps this semester] | C34: None — support role only | D34: 3 items: #49–50, 76 | E34: =IF(MIN(IF(Tracker!$G$57="Done",99999,Tracker!$F$57),IF(Tracker!$G$58="Done",99999,Tracker!$F$58))=99999,"—",MIN(IF(Tracker!$G$57="Done",99999,Tracker!$F$57),IF(Tracker!$G$58="Done",99999,Tracker!$F$58)))
A35: Ramos, Leandro M. | B35: Curriculum & Syllabi — BSCRIM; Library Collection [FT, 18 units, 4 preps this semester] | C35: None — support role only | D35: 5 items: #49–50, 66–67, 76 | E35: =IF(MIN(IF(Tracker!$G$57="Done",99999,Tracker!$F$57),IF(Tracker!$G$58="Done",99999,Tracker!$F$58),IF(Tracker!$G$75="Done",99999,Tracker!$F$75),IF(Tracker!$G$76="Done",99999,Tracker!$F$76))=99999,"—",MIN(IF(Tracker!$G$57="Done",99999,Tracker!$F$57),IF(Tracker!$G$58="Done",99999,Tracker!$F$58),IF(Tracker!$G$75="Done",99999,Tracker!$F$75),IF(Tracker!$G$76="Done",99999,Tracker!$F$76)))
A36: COMPUTER SCIENCE — Curriculum & Syllabi Committee for BSCS (chaired by Chair Diamat) (1 full-time faculty tasked; 5 part-time not tasked)
A37: Cristobal, Teofilo G. | B37: Curriculum & Syllabi — BSCS [FT, 24 units, 3 preps this semester] | C37: None — support role only | D37: 3 items: #37–38, 78 | E37: =IF(MIN(IF(Tracker!$G$45="Done",99999,Tracker!$F$45),IF(Tracker!$G$46="Done",99999,Tracker!$F$46))=99999,"—",MIN(IF(Tracker!$G$45="Done",99999,Tracker!$F$45),IF(Tracker!$G$46="Done",99999,Tracker!$F$46)))
A38: HOSPITALITY MANAGEMENT — Curriculum & Syllabi Committee for BSHM (chaired by Chair Ciasico) (3 full-time faculty tasked; 5 part-time not tasked)
A39: Bernardo, Romeo DG | B39: Curriculum & Syllabi — BSHM; Library Collection [FT, 21 units, 4 preps this semester] | C39: None — support role only | D39: 7 items: #43–44, 66–69, 77 | E39: =IF(MIN(IF(Tracker!$G$51="Done",99999,Tracker!$F$51),IF(Tracker!$G$52="Done",99999,Tracker!$F$52),IF(Tracker!$G$75="Done",99999,Tracker!$F$75),IF(Tracker!$G$76="Done",99999,Tracker!$F$76),IF(Tracker!$G$77="Done",99999,Tracker!$F$77),IF(Tracker!$G$78="Done",99999,Tracker!$F$78))=99999,"—",MIN(IF(Tracker!$G$51="Done",99999,Tracker!$F$51),IF(Tracker!$G$52="Done",99999,Tracker!$F$52),IF(Tracker!$G$75="Done",99999,Tracker!$F$75),IF(Tracker!$G$76="Done",99999,Tracker!$F$76),IF(Tracker!$G$77="Done",99999,Tracker!$F$77),IF(Tracker!$G$78="Done",99999,Tracker!$F$78)))
A40: Dela Cruz, Jonathan | B40: Curriculum & Syllabi — BSHM; Feasibility & Market Study [FT, 18 units, 4 preps this semester] | C40: None — support role only | D40: 6 items: #4–6, 43–44, 77 | E40: =IF(MIN(IF(Tracker!$G$10="Done",99999,Tracker!$F$10),IF(Tracker!$G$11="Done",99999,Tracker!$F$11),IF(Tracker!$G$12="Done",99999,Tracker!$F$12),IF(Tracker!$G$51="Done",99999,Tracker!$F$51),IF(Tracker!$G$52="Done",99999,Tracker!$F$52))=99999,"—",MIN(IF(Tracker!$G$10="Done",99999,Tracker!$F$10),IF(Tracker!$G$11="Done",99999,Tracker!$F$11),IF(Tracker!$G$12="Done",99999,Tracker!$F$12),IF(Tracker!$G$51="Done",99999,Tracker!$F$51),IF(Tracker!$G$52="Done",99999,Tracker!$F$52)))
A41: Geronimo, Jing Feng A., LPT | B41: Curriculum & Syllabi — BSHM [FT, 24 units, 4 preps this semester] | C41: None — support role only | D41: 3 items: #43–44, 77 | E41: =IF(MIN(IF(Tracker!$G$51="Done",99999,Tracker!$F$51),IF(Tracker!$G$52="Done",99999,Tracker!$F$52))=99999,"—",MIN(IF(Tracker!$G$51="Done",99999,Tracker!$F$51),IF(Tracker!$G$52="Done",99999,Tracker!$F$52)))
A42: TEACHER EDUCATION — Curriculum & Syllabi Committee for BEED and BSED (chaired by Chair K. Garcia) (14 full-time faculty tasked; 4 part-time not tasked)
A43: Ablaya, Stephanie | B43: Curriculum & Syllabi — BEED/BSED; Feasibility & Market Study [FT, 27 units, 6 preps this semester] | C43: None — support role only | D43: 8 items: #4–6, 55–56, 61–62, 79 | E43: =IF(MIN(IF(Tracker!$G$10="Done",99999,Tracker!$F$10),IF(Tracker!$G$11="Done",99999,Tracker!$F$11),IF(Tracker!$G$12="Done",99999,Tracker!$F$12),IF(Tracker!$G$63="Done",99999,Tracker!$F$63),IF(Tracker!$G$64="Done",99999,Tracker!$F$64),IF(Tracker!$G$69="Done",99999,Tracker!$F$69),IF(Tracker!$G$70="Done",99999,Tracker!$F$70))=99999,"—",MIN(IF(Tracker!$G$10="Done",99999,Tracker!$F$10),IF(Tracker!$G$11="Done",99999,Tracker!$F$11),IF(Tracker!$G$12="Done",99999,Tracker!$F$12),IF(Tracker!$G$63="Done",99999,Tracker!$F$63),IF(Tracker!$G$64="Done",99999,Tracker!$F$64),IF(Tracker!$G$69="Done",99999,Tracker!$F$69),IF(Tracker!$G$70="Done",99999,Tracker!$F$70)))
A44: Aquino, Agnes M., Dr. | B44: Curriculum & Syllabi — BEED/BSED. Writes the course descriptions and OBE syllabi for the BEED and BSED major courses allocated to her under item 79, due 25 Sep 2026. Moved out of the General Education Syllabi Pool on 13 Sep 2026 so the major-course load is not carried on top of the college-wide general education work. [FT, 24 units, 7 preps this semester] | C44: None — support role only | D44: 5 items: #55–56, 61–62, 79 | E44: =IF(MIN(IF(Tracker!$G$27="Done",99999,Tracker!$F$27),IF(Tracker!$G$28="Done",99999,Tracker!$F$28),IF(Tracker!$G$33="Done",99999,Tracker!$F$33),IF(Tracker!$G$34="Done",99999,Tracker!$F$34),IF(Tracker!$G$39="Done",99999,Tracker!$F$39),IF(Tracker!$G$40="Done",99999,Tracker!$F$40),IF(Tracker!$G$45="Done",99999,Tracker!$F$45),IF(Tracker!$G$46="Done",99999,Tracker!$F$46),IF(Tracker!$G$51="Done",99999,Tracker!$F$51),IF(Tracker!$G$52="Done",99999,Tracker!$F$52),IF(Tracker!$G$57="Done",99999,Tracker!$F$57),IF(Tracker!$G$58="Done",99999,Tracker!$F$58),IF(Tracker!$G$63="Done",99999,Tracker!$F$63),IF(Tracker!$G$64="Done",99999,Tracker!$F$64),IF(Tracker!$G$69="Done",99999,Tracker!$F$69),IF(Tracker!$G$70="Done",99999,Tracker!$F$70))=99999,"—",MIN(IF(Tracker!$G$27="Done",99999,Tracker!$F$27),IF(Tracker!$G$28="Done",99999,Tracker!$F$28),IF(Tracker!$G$33="Done",99999,Tracker!$F$33),IF(Tracker!$G$34="Done",99999,Tracker!$F$34),IF(Tracker!$G$39="Done",99999,Tracker!$F$39),IF(Tracker!$G$40="Done",99999,Tracker!$F$40),IF(Tracker!$G$45="Done",99999,Tracker!$F$45),IF(Tracker!$G$46="Done",99999,Tracker!$F$46),IF(Tracker!$G$51="Done",99999,Tracker!$F$51),IF(Tracker!$G$52="Done",99999,Tracker!$F$52),IF(Tracker!$G$57="Done",99999,Tracker!$F$57),IF(Tracker!$G$58="Done",99999,Tracker!$F$58),IF(Tracker!$G$63="Done",99999,Tracker!$F$63),IF(Tracker!$G$64="Done",99999,Tracker!$F$64),IF(Tracker!$G$69="Done",99999,Tracker!$F$69),IF(Tracker!$G$70="Done",99999,Tracker!$F$70)))
A45: Cajucom, Ryan Neil | B45: Curriculum & Syllabi — BEED/BSED [FT, 27 units, 6 preps this semester] | C45: None — support role only | D45: 5 items: #55–56, 61–62, 79 | E45: =IF(MIN(IF(Tracker!$G$63="Done",99999,Tracker!$F$63),IF(Tracker!$G$64="Done",99999,Tracker!$F$64),IF(Tracker!$G$69="Done",99999,Tracker!$F$69),IF(Tracker!$G$70="Done",99999,Tracker!$F$70))=99999,"—",MIN(IF(Tracker!$G$63="Done",99999,Tracker!$F$63),IF(Tracker!$G$64="Done",99999,Tracker!$F$64),IF(Tracker!$G$69="Done",99999,Tracker!$F$69),IF(Tracker!$G$70="Done",99999,Tracker!$F$70)))
A46: Calma, Shiela Mae C. | B46: General Education Syllabi Pool writer (item 74) — writes the course description AND the OBE syllabus for 3 courses, one set serving all 8 programmes: PATH-FIT 1 Movement Competency Training; PATH-FIT 2 Exercise-Based Fitness Activities; NSTP 1 Civic Welfare Training Service 1. 6 documents. To Chair K. Garcia: descriptions 9 Oct, syllabi 16 Oct 2026. Also Curriculum & Syllabi — BEED/BSED (not allocated BEED/BSED major courses under item 79 while carrying this pool load). [FT, 24 units, 4 preps this semester] | C46: None — support role only | D46: 17 items: #19–20, 25–26, 31–32, 37–38, 43–44, 49–50, 55–56, 61–62, 74 | E46: =IF(MIN(IF(Tracker!$G$27="Done",99999,Tracker!$F$27),IF(Tracker!$G$28="Done",99999,Tracker!$F$28),IF(Tracker!$G$33="Done",99999,Tracker!$F$33),IF(Tracker!$G$34="Done",99999,Tracker!$F$34),IF(Tracker!$G$39="Done",99999,Tracker!$F$39),IF(Tracker!$G$40="Done",99999,Tracker!$F$40),IF(Tracker!$G$45="Done",99999,Tracker!$F$45),IF(Tracker!$G$46="Done",99999,Tracker!$F$46),IF(Tracker!$G$51="Done",99999,Tracker!$F$51),IF(Tracker!$G$52="Done",99999,Tracker!$F$52),IF(Tracker!$G$57="Done",99999,Tracker!$F$57),IF(Tracker!$G$58="Done",99999,Tracker!$F$58),IF(Tracker!$G$63="Done",99999,Tracker!$F$63),IF(Tracker!$G$64="Done",99999,Tracker!$F$64),IF(Tracker!$G$69="Done",99999,Tracker!$F$69),IF(Tracker!$G$70="Done",99999,Tracker!$F$70))=99999,"—",MIN(IF(Tracker!$G$27="Done",99999,Tracker!$F$27),IF(Tracker!$G$28="Done",99999,Tracker!$F$28),IF(Tracker!$G$33="Done",99999,Tracker!$F$33),IF(Tracker!$G$34="Done",99999,Tracker!$F$34),IF(Tracker!$G$39="Done",99999,Tracker!$F$39),IF(Tracker!$G$40="Done",99999,Tracker!$F$40),IF(Tracker!$G$45="Done",99999,Tracker!$F$45),IF(Tracker!$G$46="Done",99999,Tracker!$F$46),IF(Tracker!$G$51="Done",99999,Tracker!$F$51),IF(Tracker!$G$52="Done",99999,Tracker!$F$52),IF(Tracker!$G$57="Done",99999,Tracker!$F$57),IF(Tracker!$G$58="Done",99999,Tracker!$F$58),IF(Tracker!$G$63="Done",99999,Tracker!$F$63),IF(Tracker!$G$64="Done",99999,Tracker!$F$64),IF(Tracker!$G$69="Done",99999,Tracker!$F$69),IF(Tracker!$G$70="Done",99999,Tracker!$F$70)))
A47: Delos Reyes, Diana Maris | B47: Curriculum & Syllabi — BEED/BSED [FT, 27 units, 7 preps this semester] | C47: None — support role only | D47: 5 items: #55–56, 61–62, 79 | E47: =IF(MIN(IF(Tracker!$G$63="Done",99999,Tracker!$F$63),IF(Tracker!$G$64="Done",99999,Tracker!$F$64),IF(Tracker!$G$69="Done",99999,Tracker!$F$69),IF(Tracker!$G$70="Done",99999,Tracker!$F$70))=99999,"—",MIN(IF(Tracker!$G$63="Done",99999,Tracker!$F$63),IF(Tracker!$G$64="Done",99999,Tracker!$F$64),IF(Tracker!$G$69="Done",99999,Tracker!$F$69),IF(Tracker!$G$70="Done",99999,Tracker!$F$70)))
A48: Germino, Melanie | B48: Curriculum & Syllabi — BEED/BSED [FT, 27 units, 7 preps this semester] Joins the General Education Syllabi Pool for HIS-GEC (item 74), reallocated from D. Maglalang on her resignation. | C48: None — support role only | D48: 5 items: #55–56, 61–62, 79, 74 | E48: =IF(MIN(IF(Tracker!$G$63="Done",99999,Tracker!$F$63),IF(Tracker!$G$64="Done",99999,Tracker!$F$64),IF(Tracker!$G$69="Done",99999,Tracker!$F$69),IF(Tracker!$G$70="Done",99999,Tracker!$F$70))=99999,"—",MIN(IF(Tracker!$G$63="Done",99999,Tracker!$F$63),IF(Tracker!$G$64="Done",99999,Tracker!$F$64),IF(Tracker!$G$69="Done",99999,Tracker!$F$69),IF(Tracker!$G$70="Done",99999,Tracker!$F$70)))
A49: Ilag, Ferdinand T. | B49: General Education Syllabi Pool writer (item 74) — writes the course description AND the OBE syllabus for 3 courses, one set serving all 8 programmes: REL-GEC Religion, Religious Experience and Spirituality; CLE 1 Church and Salvation History; STS-GEC Science, Technology and Society. 6 documents. To Chair K. Garcia: descriptions 9 Oct, syllabi 16 Oct 2026. Also Curriculum & Syllabi — BEED/BSED (not allocated BEED/BSED major courses under item 79 while carrying this pool load). [FT, 21 units, 3 preps this semester] Also CLE 2 (item 74), reallocated from D. Maglalang. | C49: None — support role only | D49: 17 items: #19–20, 25–26, 31–32, 37–38, 43–44, 49–50, 55–56, 61–62, 74 | E49: =IF(MIN(IF(Tracker!$G$27="Done",99999,Tracker!$F$27),IF(Tracker!$G$28="Done",99999,Tracker!$F$28),IF(Tracker!$G$33="Done",99999,Tracker!$F$33),IF(Tracker!$G$34="Done",99999,Tracker!$F$34),IF(Tracker!$G$39="Done",99999,Tracker!$F$39),IF(Tracker!$G$40="Done",99999,Tracker!$F$40),IF(Tracker!$G$45="Done",99999,Tracker!$F$45),IF(Tracker!$G$46="Done",99999,Tracker!$F$46),IF(Tracker!$G$51="Done",99999,Tracker!$F$51),IF(Tracker!$G$52="Done",99999,Tracker!$F$52),IF(Tracker!$G$57="Done",99999,Tracker!$F$57),IF(Tracker!$G$58="Done",99999,Tracker!$F$58),IF(Tracker!$G$63="Done",99999,Tracker!$F$63),IF(Tracker!$G$64="Done",99999,Tracker!$F$64),IF(Tracker!$G$69="Done",99999,Tracker!$F$69),IF(Tracker!$G$70="Done",99999,Tracker!$F$70))=99999,"—",MIN(IF(Tracker!$G$27="Done",99999,Tracker!$F$27),IF(Tracker!$G$28="Done",99999,Tracker!$F$28),IF(Tracker!$G$33="Done",99999,Tracker!$F$33),IF(Tracker!$G$34="Done",99999,Tracker!$F$34),IF(Tracker!$G$39="Done",99999,Tracker!$F$39),IF(Tracker!$G$40="Done",99999,Tracker!$F$40),IF(Tracker!$G$45="Done",99999,Tracker!$F$45),IF(Tracker!$G$46="Done",99999,Tracker!$F$46),IF(Tracker!$G$51="Done",99999,Tracker!$F$51),IF(Tracker!$G$52="Done",99999,Tracker!$F$52),IF(Tracker!$G$57="Done",99999,Tracker!$F$57),IF(Tracker!$G$58="Done",99999,Tracker!$F$58),IF(Tracker!$G$63="Done",99999,Tracker!$F$63),IF(Tracker!$G$64="Done",99999,Tracker!$F$64),IF(Tracker!$G$69="Done",99999,Tracker!$F$69),IF(Tracker!$G$70="Done",99999,Tracker!$F$70)))
A50: Jamlang, Jamie A. | B50: General Education Syllabi Pool writer (item 74) — writes the course description AND the OBE syllabus for 2 courses, one set serving all 8 programmes: CON-GEC The Contemporary World; ITE-GEC Living in the I.T. Era. 4 documents. To Chair K. Garcia: descriptions 9 Oct, syllabi 16 Oct 2026. Also Curriculum & Syllabi — BEED/BSED (not allocated BEED/BSED major courses under item 79 while carrying this pool load). [FT, 27 units, 5 preps this semester] Also RIZ-GEC (item 74), reallocated from D. Maglalang. | C50: None — support role only | D50: 17 items: #19–20, 25–26, 31–32, 37–38, 43–44, 49–50, 55–56, 61–62, 74 | E50: =IF(MIN(IF(Tracker!$G$27="Done",99999,Tracker!$F$27),IF(Tracker!$G$28="Done",99999,Tracker!$F$28),IF(Tracker!$G$33="Done",99999,Tracker!$F$33),IF(Tracker!$G$34="Done",99999,Tracker!$F$34),IF(Tracker!$G$39="Done",99999,Tracker!$F$39),IF(Tracker!$G$40="Done",99999,Tracker!$F$40),IF(Tracker!$G$45="Done",99999,Tracker!$F$45),IF(Tracker!$G$46="Done",99999,Tracker!$F$46),IF(Tracker!$G$51="Done",99999,Tracker!$F$51),IF(Tracker!$G$52="Done",99999,Tracker!$F$52),IF(Tracker!$G$57="Done",99999,Tracker!$F$57),IF(Tracker!$G$58="Done",99999,Tracker!$F$58),IF(Tracker!$G$63="Done",99999,Tracker!$F$63),IF(Tracker!$G$64="Done",99999,Tracker!$F$64),IF(Tracker!$G$69="Done",99999,Tracker!$F$69),IF(Tracker!$G$70="Done",99999,Tracker!$F$70))=99999,"—",MIN(IF(Tracker!$G$27="Done",99999,Tracker!$F$27),IF(Tracker!$G$28="Done",99999,Tracker!$F$28),IF(Tracker!$G$33="Done",99999,Tracker!$F$33),IF(Tracker!$G$34="Done",99999,Tracker!$F$34),IF(Tracker!$G$39="Done",99999,Tracker!$F$39),IF(Tracker!$G$40="Done",99999,Tracker!$F$40),IF(Tracker!$G$45="Done",99999,Tracker!$F$45),IF(Tracker!$G$46="Done",99999,Tracker!$F$46),IF(Tracker!$G$51="Done",99999,Tracker!$F$51),IF(Tracker!$G$52="Done",99999,Tracker!$F$52),IF(Tracker!$G$57="Done",99999,Tracker!$F$57),IF(Tracker!$G$58="Done",99999,Tracker!$F$58),IF(Tracker!$G$63="Done",99999,Tracker!$F$63),IF(Tracker!$G$64="Done",99999,Tracker!$F$64),IF(Tracker!$G$69="Done",99999,Tracker!$F$69),IF(Tracker!$G$70="Done",99999,Tracker!$F$70)))
A51: Manuel, Consuelo V., Dr. | B51: General Education Syllabi Pool writer (item 74) — writes the course description AND the OBE syllabus for 3 courses, one set serving all 8 programmes: ETH-GEC Ethics; MAT-GEC Mathematics in the Modern World; BL-GEC Business Logic. 6 documents. To Chair K. Garcia: descriptions 9 Oct, syllabi 16 Oct 2026. Also Curriculum & Syllabi — BEED/BSED (not allocated BEED/BSED major courses under item 79 while carrying this pool load). [FT, 24 units, 4 preps this semester] | C51: None — support role only | D51: 17 items: #19–20, 25–26, 31–32, 37–38, 43–44, 49–50, 55–56, 61–62, 74 | E51: =IF(MIN(IF(Tracker!$G$27="Done",99999,Tracker!$F$27),IF(Tracker!$G$28="Done",99999,Tracker!$F$28),IF(Tracker!$G$33="Done",99999,Tracker!$F$33),IF(Tracker!$G$34="Done",99999,Tracker!$F$34),IF(Tracker!$G$39="Done",99999,Tracker!$F$39),IF(Tracker!$G$40="Done",99999,Tracker!$F$40),IF(Tracker!$G$45="Done",99999,Tracker!$F$45),IF(Tracker!$G$46="Done",99999,Tracker!$F$46),IF(Tracker!$G$51="Done",99999,Tracker!$F$51),IF(Tracker!$G$52="Done",99999,Tracker!$F$52),IF(Tracker!$G$57="Done",99999,Tracker!$F$57),IF(Tracker!$G$58="Done",99999,Tracker!$F$58),IF(Tracker!$G$63="Done",99999,Tracker!$F$63),IF(Tracker!$G$64="Done",99999,Tracker!$F$64),IF(Tracker!$G$69="Done",99999,Tracker!$F$69),IF(Tracker!$G$70="Done",99999,Tracker!$F$70))=99999,"—",MIN(IF(Tracker!$G$27="Done",99999,Tracker!$F$27),IF(Tracker!$G$28="Done",99999,Tracker!$F$28),IF(Tracker!$G$33="Done",99999,Tracker!$F$33),IF(Tracker!$G$34="Done",99999,Tracker!$F$34),IF(Tracker!$G$39="Done",99999,Tracker!$F$39),IF(Tracker!$G$40="Done",99999,Tracker!$F$40),IF(Tracker!$G$45="Done",99999,Tracker!$F$45),IF(Tracker!$G$46="Done",99999,Tracker!$F$46),IF(Tracker!$G$51="Done",99999,Tracker!$F$51),IF(Tracker!$G$52="Done",99999,Tracker!$F$52),IF(Tracker!$G$57="Done",99999,Tracker!$F$57),IF(Tracker!$G$58="Done",99999,Tracker!$F$58),IF(Tracker!$G$63="Done",99999,Tracker!$F$63),IF(Tracker!$G$64="Done",99999,Tracker!$F$64),IF(Tracker!$G$69="Done",99999,Tracker!$F$69),IF(Tracker!$G$70="Done",99999,Tracker!$F$70)))
A52: Mequiabas, Meah | B52: General Education Syllabi Pool writer (item 74) — writes the course description AND the OBE syllabus for 3 courses, one set serving all 8 programmes: PATH-FIT 3 Dance; PATH-FIT 4 Sports; NSTP 2 Civic Welfare Training Service 2. 6 documents. To Chair K. Garcia: descriptions 9 Oct, syllabi 16 Oct 2026. Also Curriculum & Syllabi — BEED/BSED (not allocated BEED/BSED major courses under item 79 while carrying this pool load). [FT, 26 units, 4 preps this semester] | C52: None — support role only | D52: 17 items: #19–20, 25–26, 31–32, 37–38, 43–44, 49–50, 55–56, 61–62, 74 | E52: =IF(MIN(IF(Tracker!$G$27="Done",99999,Tracker!$F$27),IF(Tracker!$G$28="Done",99999,Tracker!$F$28),IF(Tracker!$G$33="Done",99999,Tracker!$F$33),IF(Tracker!$G$34="Done",99999,Tracker!$F$34),IF(Tracker!$G$39="Done",99999,Tracker!$F$39),IF(Tracker!$G$40="Done",99999,Tracker!$F$40),IF(Tracker!$G$45="Done",99999,Tracker!$F$45),IF(Tracker!$G$46="Done",99999,Tracker!$F$46),IF(Tracker!$G$51="Done",99999,Tracker!$F$51),IF(Tracker!$G$52="Done",99999,Tracker!$F$52),IF(Tracker!$G$57="Done",99999,Tracker!$F$57),IF(Tracker!$G$58="Done",99999,Tracker!$F$58),IF(Tracker!$G$63="Done",99999,Tracker!$F$63),IF(Tracker!$G$64="Done",99999,Tracker!$F$64),IF(Tracker!$G$69="Done",99999,Tracker!$F$69),IF(Tracker!$G$70="Done",99999,Tracker!$F$70))=99999,"—",MIN(IF(Tracker!$G$27="Done",99999,Tracker!$F$27),IF(Tracker!$G$28="Done",99999,Tracker!$F$28),IF(Tracker!$G$33="Done",99999,Tracker!$F$33),IF(Tracker!$G$34="Done",99999,Tracker!$F$34),IF(Tracker!$G$39="Done",99999,Tracker!$F$39),IF(Tracker!$G$40="Done",99999,Tracker!$F$40),IF(Tracker!$G$45="Done",99999,Tracker!$F$45),IF(Tracker!$G$46="Done",99999,Tracker!$F$46),IF(Tracker!$G$51="Done",99999,Tracker!$F$51),IF(Tracker!$G$52="Done",99999,Tracker!$F$52),IF(Tracker!$G$57="Done",99999,Tracker!$F$57),IF(Tracker!$G$58="Done",99999,Tracker!$F$58),IF(Tracker!$G$63="Done",99999,Tracker!$F$63),IF(Tracker!$G$64="Done",99999,Tracker!$F$64),IF(Tracker!$G$69="Done",99999,Tracker!$F$69),IF(Tracker!$G$70="Done",99999,Tracker!$F$70)))
A53: Sta. Cruz, Ma. Patricia | B53: Curriculum & Syllabi — BEED/BSED; Library Collection [FT, 27 units, 3 preps this semester] | C53: None — support role only | D53: 9 items: #55–56, 61–62, 66–69, 79 | E53: =IF(MIN(IF(Tracker!$G$63="Done",99999,Tracker!$F$63),IF(Tracker!$G$64="Done",99999,Tracker!$F$64),IF(Tracker!$G$69="Done",99999,Tracker!$F$69),IF(Tracker!$G$70="Done",99999,Tracker!$F$70),IF(Tracker!$G$75="Done",99999,Tracker!$F$75),IF(Tracker!$G$76="Done",99999,Tracker!$F$76),IF(Tracker!$G$77="Done",99999,Tracker!$F$77),IF(Tracker!$G$78="Done",99999,Tracker!$F$78))=99999,"—",MIN(IF(Tracker!$G$63="Done",99999,Tracker!$F$63),IF(Tracker!$G$64="Done",99999,Tracker!$F$64),IF(Tracker!$G$69="Done",99999,Tracker!$F$69),IF(Tracker!$G$70="Done",99999,Tracker!$F$70),IF(Tracker!$G$75="Done",99999,Tracker!$F$75),IF(Tracker!$G$76="Done",99999,Tracker!$F$76),IF(Tracker!$G$77="Done",99999,Tracker!$F$77),IF(Tracker!$G$78="Done",99999,Tracker!$F$78)))
A54: Tolosa, Nenita | B54: General Education Syllabi Pool writer (item 74) — writes the course description AND the OBE syllabus for 3 courses, one set serving all 8 programmes: ART-GEC Art Appreciation; COM-GEC Purposive Communication; US-GEC Understanding the Self. 6 documents. To Chair K. Garcia: descriptions 9 Oct, syllabi 16 Oct 2026. Also Curriculum & Syllabi — BEED/BSED (not allocated BEED/BSED major courses under item 79 while carrying this pool load). [FT, 24 units, 5 preps this semester] | C54: None — support role only | D54: 17 items: #19–20, 25–26, 31–32, 37–38, 43–44, 49–50, 55–56, 61–62, 74 | E54: =IF(MIN(IF(Tracker!$G$27="Done",99999,Tracker!$F$27),IF(Tracker!$G$28="Done",99999,Tracker!$F$28),IF(Tracker!$G$33="Done",99999,Tracker!$F$33),IF(Tracker!$G$34="Done",99999,Tracker!$F$34),IF(Tracker!$G$39="Done",99999,Tracker!$F$39),IF(Tracker!$G$40="Done",99999,Tracker!$F$40),IF(Tracker!$G$45="Done",99999,Tracker!$F$45),IF(Tracker!$G$46="Done",99999,Tracker!$F$46),IF(Tracker!$G$51="Done",99999,Tracker!$F$51),IF(Tracker!$G$52="Done",99999,Tracker!$F$52),IF(Tracker!$G$57="Done",99999,Tracker!$F$57),IF(Tracker!$G$58="Done",99999,Tracker!$F$58),IF(Tracker!$G$63="Done",99999,Tracker!$F$63),IF(Tracker!$G$64="Done",99999,Tracker!$F$64),IF(Tracker!$G$69="Done",99999,Tracker!$F$69),IF(Tracker!$G$70="Done",99999,Tracker!$F$70))=99999,"—",MIN(IF(Tracker!$G$27="Done",99999,Tracker!$F$27),IF(Tracker!$G$28="Done",99999,Tracker!$F$28),IF(Tracker!$G$33="Done",99999,Tracker!$F$33),IF(Tracker!$G$34="Done",99999,Tracker!$F$34),IF(Tracker!$G$39="Done",99999,Tracker!$F$39),IF(Tracker!$G$40="Done",99999,Tracker!$F$40),IF(Tracker!$G$45="Done",99999,Tracker!$F$45),IF(Tracker!$G$46="Done",99999,Tracker!$F$46),IF(Tracker!$G$51="Done",99999,Tracker!$F$51),IF(Tracker!$G$52="Done",99999,Tracker!$F$52),IF(Tracker!$G$57="Done",99999,Tracker!$F$57),IF(Tracker!$G$58="Done",99999,Tracker!$F$58),IF(Tracker!$G$63="Done",99999,Tracker!$F$63),IF(Tracker!$G$64="Done",99999,Tracker!$F$64),IF(Tracker!$G$69="Done",99999,Tracker!$F$69),IF(Tracker!$G$70="Done",99999,Tracker!$F$70)))
A55: Villamayor, Xyrelle | B55: Curriculum & Syllabi — BEED/BSED [FT, 27 units, 6 preps this semester] | C55: None — support role only | D55: 5 items: #55–56, 61–62, 79 | E55: =IF(MIN(IF(Tracker!$G$63="Done",99999,Tracker!$F$63),IF(Tracker!$G$64="Done",99999,Tracker!$F$64),IF(Tracker!$G$69="Done",99999,Tracker!$F$69),IF(Tracker!$G$70="Done",99999,Tracker!$F$70))=99999,"—",MIN(IF(Tracker!$G$63="Done",99999,Tracker!$F$63),IF(Tracker!$G$64="Done",99999,Tracker!$F$64),IF(Tracker!$G$69="Done",99999,Tracker!$F$69),IF(Tracker!$G$70="Done",99999,Tracker!$F$70)))
A57: PART-TIME FACULTY — NOT TASKED
A58: 21 part-time faculty | B58: Listed on the Faculty sheet because checklist item 5.1 requires every faculty member teaching general education and major courses. They carry no project tasks and sit on no committee. Aberin, Gabriel Angelo, Adiova, Marites, Alarcon, Leuz Rafael, Cabrera, Francis, Carasco, Ryan Jay, Corpuz, Alpha Jessa, Cruz, Rommel, Empay, Jan Rhommer, Fernando, Eddyson S., Francisco, Jayson R., Francisco, Josephine Rose, Garcia, Michael Johnrein, Gomez, Donna Michelle A., Magdaong, Jennifer, Mariano, Jerick, Patiag, Glaiza Kaye, Patiag, Mark, Peralta, Ronel Evan P., Santiago, Decirae Nicole, Santos, John Vincent L., Timpac, Theodore M. | C58: — | D58: — | E58: —
A60: Check | B60: =COUNT(Tracker!$A$5:$A$90)&" tracker items, each with exactly one accountable owner. "&COUNTIF(Faculty!$E$5:$E$59,"FT")&" full-time faculty tasked; "&COUNTIF(Faculty!$E$5:$E$59,"PT")&" part-time faculty not tasked."

Sheet Reference
A1: REFERENCE — SOURCES, CITATIONS, COMMITTEES AND OPEN ITEMS
A2: Everything in the Tracker traces back to one of the source documents below. Nothing has been added from general practice. Where a requirement is unclear, it is listed as an Open Item rather than guessed. The committee and borrowing structure in section F is an internal proposal for the Vice Dean's approval — it is not a CHED requirement.
A4: Section | B4: Detail
A5: A. SOURCE DOCUMENTS USED
A6: Preliminary Requirement checklist | B6: The 9-section documentary checklist held by the Office of Academic Affairs (items 1 to 9, including sub-items 3.1-3.4, 4.1-4.2, 5.1-5.3, 7.1-7.4, 8.1-8.4.4, 9.1-9.2). Sole source of Tracker items 1 to 69.
A7: Minutes of the Special Meeting of the Council of Program Chairs | B7: 27 August 2026, 10:00-11:30 AM, Office of the VPAA. Presided by VPAA Dr. Raquel T. Sta. Ines, technically facilitated by MIS Head Jayson R. Francisco, MIT, prepared by Vice Dean Ken Gie Anthony G. Cruel, CPA, MBA. Dean Dr. Almario B. Garcia on official leave.
A8: Internal project implementation plan | B8: Four-phase plan with hard deadlines of 12 Sep, 16 Oct, 30 Oct and 13 Nov 2026. Source of Tracker items 70 to 72 and of the delegation pattern used for owners.
A9: Draft trimester curriculum workbook | B9: Draft 9-term prospectus for BSA (191 units) and BSAIS (185 units), proposed AY 2027-2028 academic calendar, and the sample schedule sheet carrying the contact-hour computation. All 8 programmes are now at the same draft stage. NOTE: the calendar in this workbook was drawn on three terms of FIFTEEN academic weeks. The Council decided 14 weeks on 9 Sep 2026, so the calendar must be redrawn — including the enrolment, grade-processing and graduation dates — before any weekly schedule grid is finalised.
A10: CHED Region III Citizen's Charter (verified 3 Sep 2026) | B10: Official CHED source located and read on 3 September 2026. Its checklist for Application for Initial Permit (GP), Government Recognition (GR) and Certificate of Program Compliance (COPC) for Undergraduate Programs contains 18 numbered requirements. Items 1 and 5 to 10 correspond almost word for word to the internal Preliminary Requirement checklist - the same feasibility study headings, the same administrator and faculty spreadsheet fields, the same curriculum breakdown, and the same 3,000 and 5,000 library figures. Nine further requirements on the CHED list do not appear on the internal one: see Open Item 2. Source: https://chedro3.ched.gov.ph/wp-content/uploads/2021/01/CHEDROIII-Updated-Citizens-Charter.pdf
A11: 7.1 Distribution of Courses per Trimester — BSCRIM | B11: Received 3 Sep 2026 as the working template for checklist item 7.1, and as a complete BSCRIM prospectus in its own right (192 units, effective AY 2027-2028, citing CMO 05 s.2018 and CMO 20 s.2013). Not yet a final template - still for discussion. Its structure is set out in section C2 below.
A12: Faculty Roster, First Semester AY 2026-2027 | B12: 55 unique faculty (34 full-time, 21 part-time) across six departments, with course counts, units, weekly hours and preps. Prepared by Vice Dean Cruel, recommended by Dean Garcia, approved by VPAA Sta. Ines. Source of the Faculty sheet and of the committee membership in section E.
A14: B. COUNCIL RESOLUTIONS (27 AUGUST 2026)
A15: Resolution No. 2026-08-01 | B15: Endorsement of the proposed transition of BSA, BSAIS, BSBA, BSCS, BSHM, BSCRIM, BEED and BSED from the four-year semestral model to a 3-Year Trimester System, targeted to commence in AY 2027-2028, subject to CHED requirements.
A16: Resolution No. 2026-08-02 | B16: New curriculum to apply initially to incoming first-year students from AY 2027-2028. Students admitted earlier continue under their year-of-admission prospectus, subject to an approved transition and teach-out plan covering irregular, returning and transferee students.
A17: Resolution No. 2026-08-03 | B17: Mobilisation of the CHED Application Task Force, co-led by Vice Dean Cruel and MIS Head Francisco under the supervision of the Office of the VPAA. Target completion and submission of the consolidated dossier on or before 13 November 2026.
A19: C. CHED ISSUANCES AND AUTHORITY
A20: CMO No. 27 and CMO No. 30, series of 2017 | B20: Cited in the draft curriculum workbook as the basis for BSA and BSAIS contact hours: at least 14 contact hours per unit offered, which is 42 hours for a 3-unit subject. This is the regulatory FLOOR.
A21: College standard: 54 hours per 3-unit subject (superseded) | B21: SUPERSEDED 9 Sep 2026. Was 54 hours, set by the Vice Dean on 3 Sep 2026 when the term length was still open. Now 56 hours per 3-unit subject — see the Contact-hour standard entry in section D2.
A22: No CMO governs the checklist | B22: The internal Preliminary Requirement checklist carries no CMO number, series year or annex - and neither does CHED's own version. The CHED Region III Citizen's Charter presents the same requirements as a GPR Checklist and cites only Section 8 of Republic Act No. 7722, the Higher Education Act of 1994, as the general authority. So the missing CMO is not an omission by the college. Every Tracker row is cited to a checklist item number, which matches how CHED itself presents them. See Open Item 3.
A24: C2. THE CURRICULUM TEMPLATE (from the BSCRIM submission, 3 Sep 2026 - not yet final)
A25: Header | B25: Programme name in full. 'Effective Academic Year 2027-2028'. A References line citing that programme's own PSG - BSCRIM uses CMO 05 s.2018 and CMO 20 s.2013; BSA and BSAIS use CMO 27 and CMO 30 s.2017. This is how each row in the dossier gets a real citation: per programme, from its own PSG.
A26: Year groupings | B26: Three named years - the BSCRIM draft uses YEAR I: CORE FOUNDATIONS, YEAR II: PROFESSIONAL SUBJECTS, YEAR III: SPECIALIZATION - each holding three trimesters, numbered Trimester 1 through 9 straight through.
A27: Table columns | B27: Course Code | Course Title | Lec Hrs | Lab Hrs | Total Hrs | Credit Units | Prerequisite(s). One table per trimester, closing with a Sub-Total row that foots all four numeric columns.
A28: Summary table (checklist item 7.2) | B28: Units by category code, then the total: the BSCRIM draft gives GEC 33 (GE Core plus Rizal), GEE 15, PE 8, NSTP 6, Core 19, Major 105, OJT 6, total 192.
A29: Closing note | B29: 'Registration in any course is allowed only upon passing the prerequisite(s) of the said course, if any. A course enrolled in violation of this rule will not be given any credit regardless of the grade obtained.'
A30: Sign-off chain | B30: Prepared by: Programme Chairperson. Reviewed by: ALMARIO B. GARCIA, Ph.D., College Dean. Approved by: RAQUEL T. STA INES, Ph.D., Vice President for Academic Affairs. Every programme's item 7.1 follows this route.
A31: UNRESOLVED - what basis are the Hrs columns? | B31: In the BSCRIM draft a 3-unit lecture course reads 3 Lec Hrs, 3 Total Hrs. Those are WEEKLY hours on the old semestral convention: 3 hours a week over 18 weeks is 54 hours. Under the decided 14-week trimester at 56 hours, the same course runs exactly 4.0 weekly hours — a whole number, which the 54-hour figure never gave at either term length. So the column can stay on a weekly basis and simply be restated from 3 to 4. Still to decide before eight programmes populate the template: label the columns as weekly hours (4, 0, 4) or as total term hours (56, 0, 56), or carry both. See Open Item 6.
A33: D. OPEN ITEMS — TO BE RESOLVED, NOT GUESSED
A34: Open Item 1 — RESOLVED 9 Sep 2026 | B34: RESOLVED 9 Sep 2026 — 14 WEEKS. Decided by the Council of Programme Chairs. The contact-hour standard moves from 54 to 56 hours per 3-unit subject so that the week divides into whole periods: 56 hours over 14 weeks is 240 minutes a week, which splits into 2 x 120, 3 x 80 or 4 x 60 minutes. At 54 hours it would have been 231.43 minutes, which divides into nothing usable. 56 hours is 18.67 contact hours per unit against the CMO 27 & 30 floor of 14 — 33 per cent above it, better headroom than the old 54. COSTS OF THE DECISION, recorded so they are not lost: (1) the daily student load over four teaching days rises to 8.00 hours on a 24-unit term and 8.33 on the two 25-unit BSCRIM trimesters; (2) the proposed AY 2027-2028 calendar was drawn on FIFTEEN academic weeks and must be redrawn. TWO THINGS STILL OWED FOR THE DOSSIER: the Council meeting date and the resolution number covering this decision. Note also that the CMO 27 & 30 floor has only been read for BSA and BSAIS — each Chair still owes a check against their own PSG before the dossier states that 56 hours clears the floor for all eight.
A35: Open Item 2 | B35: Does the full CHED Region III GPR checklist apply to this application? The internal Preliminary Requirement checklist has 9 sections. The CHED Region III Citizen's Charter checklist for Application for Initial Permit / Government Recognition / COPC for Undergraduate Programs has 18, and items 1 and 5 to 10 match the internal checklist almost word for word - which strongly suggests the internal checklist was drawn from it. Nine requirements on the CHED list do not appear on the internal one at all: Articles of Incorporation and By-Laws; Transfer Certificate of Title, lease contract or proof of ownership of the school building; Certificate of Occupancy in the name of the HEI indicating educational purpose; physical facilities (site, floor area, buildings, classrooms, laboratories); equipment and instructional devices; support facilities (audio-visual room, sports, canteen, lounges); support services (guidance, medical and dental); NSTP coordinator and office; and the school bond of P6,000 plus an application fee of P4,000 and an inspection fee of P4,000. They are NOT in the tracker, because the internal checklist is the agreed source of truth and adding them would be a guess. If Region III confirms they apply, nine rows have to be added and several of them - occupancy certificate, facilities inventory - take real lead time. This is the single most consequential question on the list. [ Ask: MIS Head Francisco - tracker item 73, ask first ]
A36: Open Item 3 | B36: Which route, and therefore which library threshold? The CHED Region III charter distinguishes an INITIAL PERMIT (3,000 library collections) from RECOGNITION (5,000). The eight programmes already exist; only the delivery changes from semestral to trimestral. Confirm whether Region III treats a change in term system as a new permit application, an amendment to existing recognition, or something else - the answer sets the library target for item 68 and decides Open Item 2 with it. Note also that CHED's own charter cites no Memorandum Order for this checklist, only Section 8 of Republic Act No. 7722 as the general authority; so the absence of a CMO on the internal checklist is not an oversight by the college. [ Ask: MIS Head Francisco - tracker item 73 ]
A37: Open Item 4 | B37: Number of hard copy binders and the soft copy format required by CHED Region III on filing. Note that the charter also lists a school bond and application and inspection fees - confirm whether those are payable here (see Open Item 2). [ Ask: MIS Head Francisco - tracker item 73 ]
A38: Open Item 5 | B38: HIGHEST WORKLOAD IMPACT. Checklist item 7.4 - are course syllabi required for every course in all 8 programmes, or only for new and re-sequenced courses? The answer governs the 16 October deadline on items 15 to 62 and decides how serious Open Item 8 below really is. [ Ask: MIS Head Francisco - tracker item 73, due 25 Sep ]
A39: Open Item 6 | B39: THE TEMPLATE EXISTS BUT ITS HOURS COLUMNS ARE UNDEFINED. The BSCRIM submission of 3 Sep 2026 is the working template and its structure is settled (section C2). One thing is not: the Lec, Lab and Total Hrs columns are filled in as WEEKLY hours on the old semestral convention — a 3-unit lecture course shows 3 hours, which is 3 a week over 18 weeks, exactly 54. NARROWED 9 Sep 2026 by the Council's decision on Open Item 1: at 14 weeks and 56 hours the same course runs exactly 4.0 weekly hours, a whole number, so the arithmetic no longer fights the column. What remains is purely a labelling choice — restate the column as weekly hours (4, 0, 4), as total term hours (56, 0, 56), or carry both — and it must be settled before the other seven programmes populate the template, or all eight will need reworking. [ Ask: Vice Dean / Chairs - blocks 48 rows ]
A40: Open Item 7 | B40: GENERAL EDUCATION COURSE CODES DO NOT MATCH ACROSS PROGRAMMES. The General Education Syllabi Pool exists to write each GE course ONCE for all 8 programmes, which only works if the same course carries the same code, units and hour split everywhere. Comparing the two prospectuses in hand: BSA has REL-GEC Religion, Religious Experience and Spirituality, BSCRIM has REL-GEE; BSA has ITE-GEC Living in the I.T. Era at 3 lecture hours, BSCRIM has IT-GEE Living in IT Era (Elective) at 1 lecture and 3 laboratory hours; and the four PATH-FIT courses are discipline-specific in BSCRIM (martial arts, arnis, water safety, marksmanship) against generic titles in BSA, so they cannot be pooled at all. Of the 20 courses the pool was sized on, only about 13 currently match cleanly. Harmonise the GE codes and hour splits across all 8 prospectuses, or the pool will produce syllabi that do not match half the programmes. The true pool size cannot be fixed until all 8 drafts are in. [ Ask: Vice Dean / Council of Programme Chairs ] BLOCKS ITEM 74: Chair K. Garcia cannot allocate 20 shared courses whose codes are not agreed, so this has to be settled before the General Education Syllabi Pool allocation due 25 Sep.
A41: Open Item 8 | B41: Who signs the application letter? The CHED Region III charter requires it to be signed by the Chairman of the Board of Trustees or the President, or an authorised representative. The tracker currently shows the VPAA as signatory for item 1. Confirm and, if needed, secure a board authorisation before the letter is finalised. [ Ask: Vice Dean / Board Secretary ]
A42: Open Item 9 | B42: CAPACITY, ACCEPTED BY THE VICE DEAN. With part-time faculty excluded from tasking, BSA and BSAIS have no full-time faculty besides the Chair; BSCS has two. After both college-wide pools, roughly 41 programme-specialised accountancy and AIS courses have no full-time author but the Vice Dean. He has taken this on personally - no decision is needed from anyone else. Recorded so the exposure stays visible: if Open Item 5 comes back requiring syllabi for every course, this is where the project slips first. [ Ask: Vice Dean - handling personally ]
A44: D2. RESOLVED - DECISIONS ALREADY MADE
A45: Programme chairs | B45: Kent E. Garcia chairs BOTH BEED and BSED. Confirmed by the Vice Dean, 2 Sep 2026.
A46: No Admin Office Head | B46: Dr. Raquel T. Sta. Ines is VPAA and also VP for Administration and Finance. Items 7 and 14 sit with her office. Confirmed 2 Sep 2026.
A47: Library team identity | B47: Sta. Cruz, Ma. Patricia (Teacher Education) and Bernardo, Romeo DG (Hospitality Management) on the faculty roster ARE the library team members named in the project plan - the same people, holding both roles. Confirmed 2 Sep 2026.
A48: Library Lead | B48: There is no appointed head librarian. Annabelle Pastrana is acting Library Lead and owns items 63 to 69. Confirmed 3 Sep 2026. A designation memo still has to be issued and attached to item 63.
A49: Cristobal, Teofilo G. | B49: Full-time in BSCS, not Teacher Education. The roster's main sheet lists him under Teacher Education and should be corrected before filing. Confirmed 3 Sep 2026.
A50: Checklist item 9 in-charge | B50: Owned by the Programme Chairs. Confirmed by the Vice Dean, 3 Sep 2026.
A51: Task force co-leads | B51: Dean Dr. Almario B. Garcia added as a third co-lead alongside the Vice Dean and the MIS Head. Directed by the Vice Dean, 3 Sep 2026. Note that Council Resolution 2026-08-03 as minuted designates only two co-leads - the resolution or its implementing memo should be updated to match.
A52: Transmittal letter ownership | B52: Item 1 transferred from the Vice Dean to MIS Head Francisco. Directed by the Vice Dean, 3 Sep 2026. The Vice Dean remains the author of both the transmittal letter and the minutes.
A53: CHED Program Evaluation | B53: Checklist item 2 is not a CHED form. It is a self-evaluation compilation prepared against each programme's CHED Policies, Standards and Guidelines. Confirmed by the Vice Dean, 3 Sep 2026, and corroborated by the CHED Region III Citizen's Charter, which requires a duly accomplished self-evaluation form per programme on submission.
A54: Library threshold criterion | B54: The CHED Region III charter reads: start-up 3,000 library collections for an initial permit, minimum 5,000 for recognition. The threshold turns on the filing route, not on the programme being new. Which route applies is Open Item 3.
A55: Curriculum template | B55: A working template now exists - the BSCRIM 7.1 Distribution of Courses per Trimester, received 3 Sep 2026. Structure settled (Reference section C2); final form still for discussion, and the hours basis is unresolved (Open Item 6).
A56: How each row gets a citation | B56: Per programme, from that programme's own PSG, carried in the prospectus header. BSCRIM cites CMO 05 s.2018 and CMO 20 s.2013; BSA and BSAIS cite CMO 27 and CMO 30 s.2017. This is the same logic as the PSG-based self-evaluation in checklist item 2.
... A64: Term length | B64: 14 weeks per trimester. Decided by the Council of Programme Chairs, 9 Sep 2026, closing Open Item 1. The contact-hour standard moved to 56 hours per 3-unit subject in the same decision so that the week divides into whole periods. The AY 2027-2028 academic calendar must be redrawn from 15 weeks to 14. Council meeting date and resolution number still to be supplied.
A66: E. MANPOWER - FULL-TIME CAPACITY BY DEPARTMENT
A67: Rule applied | B67: Only full-time faculty are tasked. The 21 part-time faculty stay on the Faculty sheet because checklist item 5.1 requires every faculty member teaching general education and major courses, but they carry no project work and sit on no committee.
A68: BSA & BSAIS (Accountancy / AIS) | B68: 6 faculty - 1 full-time (the Vice Dean, who is also the Chair). NO other full-time faculty. 5 part-time CPAs not tasked. The only department in the college with no full-time teaching capacity at all.
A69: BSBA (Business Administration) | B69: 6 faculty - 5 full-time, 4 taskable after the Chair. Supplies the Business Cluster Pool.
A70: BS Criminology | B70: 7 faculty - 6 full-time, 5 taskable after the Chair. Self-sufficient.
A71: BS Computer Science | B71: 7 faculty - 2 full-time: the Chair and Cristobal, Teofilo G. (confirmed by the Vice Dean as full-time in BSCS, not Teacher Education). 5 part-time not tasked.
A72: BS Hospitality Management | B72: 9 faculty - 4 full-time, 3 taskable after the Chair. Self-sufficient. Geronimo, Jing Feng A., LPT replaced Franco, Nadine Denise, who resigned.
A73: Teacher Education (BEED / BSED) | B73: 20 faculty - 16 full-time, 14 taskable after the Dean and the Chair. The only department with surplus - it supplies the General Education Syllabi Pool.
A75: F. WORKING COMMITTEES AND BORROWED MANPOWER (internal proposal - not a CHED requirement)
A76: General Education Syllabi Pool — lead: Chair Kent E. Garcia | B76: THE MAIN BORROWING. LEAD: Programme Chair Kent E. Garcia (named 9 Sep 2026). The 20 general education, PATH-FIT, NSTP and CLE courses are common to all 8 programmes, so they are written ONCE for the whole college instead of eight times — removing roughly 140 duplicated syllabi. Drawn from Teacher Education, the only department with surplus full-time capacity. WRITER ALLOCATION, revised 13 Sep 2026 — each writer produces the course description AND the OBE syllabus for every course listed: Ilag, Ferdinand T. — REL-GEC Religion, Religious Experience and Spirituality, CLE 1 Church and Salvation History, STS-GEC Science, Technology and Society. Maglalang, Danica — CLE 2 Evangelism and Discipleship, HIS-GEC Readings in Philippine History, RIZ-GEC Rizal's Life and Works. Calma, Shiela Mae C. — PATH-FIT 1 Movement Competency Training, PATH-FIT 2 Exercise-Based Fitness Activities, NSTP 1. Mequiabas, Meah — PATH-FIT 3 Dance, PATH-FIT 4 Sports, NSTP 2. Manuel, Consuelo V., Dr. — ETH-GEC Ethics, MAT-GEC Mathematics in the Modern World, BL-GEC Business Logic. Tolosa, Nenita — ART-GEC Art Appreciation, COM-GEC Purposive Communication, US-GEC Understanding the Self. Jamlang, Jamie A. — CON-GEC The Contemporary World, ITE-GEC Living in the I.T. Era (two only, on the heaviest teaching load in the pool). AQUINO, AGNES M., Dr. WAS MOVED OUT OF THIS POOL on 13 Sep 2026 by direction of the Vice Dean — she writes BEED/BSED major courses under item 79 instead, and the pool went from eight writers to seven. Internal hand-in to the lead: descriptions 9 Oct 2026, syllabi 16 Oct 2026. CAVEATS: the codes above are the BSA and BSAIS spellings and Open Item 7 must close before the allocation is final — it blocks item 74; and NSTP 1 is the prerequisite of NSTP 2, now with different writers, so Calma and Mequiabas must agree the pair.
A77: Business Cluster Pool — lead: Chair Ranilo S. Castillo II | B77: SECOND BORROWING. LEAD: Programme Chair Ranilo S. Castillo II (named 9 Sep 2026). The shared business, economics and law courses are written once for BSA, BSAIS, BSBA and BSHM by BSBA's four full-time faculty. CANDIDATE COURSE LIST, 13 courses, read off the BSA and BSAIS prospectus on 13 Sep 2026 and NOT YET CONFIRMED — the lead's first task under item 75 is to check each one against the BSBA and BSHM prospectuses before writing starts. WRITER ALLOCATION, issued 13 Sep 2026 — description AND OBE syllabus for each course: Salas, Kristine Joy — AE1-BL1 Law on Obligations and Contracts, AE2-BL2 Business Laws and Regulations, AE3-BL3 Regulatory Framework and Legal Issues in Business. Aquino, Ann Jellie B. — AE11-ECO1 Managerial Economics, AE12-ECO2 Economic Development, AE5-IBT International Business and Trade. Bauat, Jhosalyn — CBME 1 Operations Management and TQM, CBME 2 Strategic Management, AE4-MGT1 Management Science, PE1-HBO Human Behavior in Organizations. Dela Cruz, Jacqueline — AE19-FINMGT Financial Management, AE18-FINMKT Financial Markets, AE10-GOV Governance, Business Ethics, Risk Management and Internal Control. Bauat takes the fourth course as the only pool writer on no third committee; Dela Cruz is held to three because she also sits on the Library Collection Committee. Internal hand-in to the lead: descriptions 9 Oct 2026, syllabi 16 Oct 2026. LOAD WARNING: these same four faculty also write the BSBA major courses under item 80, on 24 units each — after the Vice Dean this is the heaviest writing load in the college, and both allocations should be published together so each writer's total is visible.
A78: Curriculum & Syllabi Committee | B78: One per programme, chaired by that Programme Chair, made up of the department's full-time faculty. Covers whatever the two pools do not — the programme-specialised courses. Each Chair publishes a departmental WRITER ALLOCATION naming which faculty member writes which major course, due 25 Sep 2026 and tracked as items 76 (BSCRIM, Chair Pisto), 77 (BSHM, Chair Ciasico), 78 (BSCS, Chair Diamat), 79 (BEED and BSED, Chair K. Garcia — the six Teacher Education faculty not in the GE pool) and 80 (BSBA, Chair Castillo). Until those are published, the 15 faculty concerned hold a counted task with fixed hand-in dates on the Faculty sheet rather than named courses. BSA and BSAIS have no full-time members here: see Open Item 9. BSCS has one, which is why item 78 carries a capacity warning.
A79: Library Collection Committee | B79: Chaired by Library Lead Pastrana. Full-time faculty, one per department: Bernardo, Romeo DG, Dela Cruz, Jacqueline, Ramos, Leandro M., Sta. Cruz, Ma. Patricia. Supports items 66 and 67; Sta. Cruz and Bernardo, who are the library team named in the project plan, also carry items 68 and 69 on top of full teaching loads. BSA/BSAIS and BSCS have too few full-time faculty to seat, so their subject title lists fall to the Chairs.
A80: Feasibility & Market Study Committee | B80: Chaired by MIS Head Francisco. Full-time faculty, one per department: Ablaya, Stephanie, Aquino, Ann Jellie B., Arimbuyutan, Jazzele M., Dela Cruz, Jonathan. Supports items 4, 5 and 6.
A81: Records & Documents | B81: Not a faculty committee. HR Officer Dela Cruz owns items 9 to 13; the VPAA, who also holds the VP for Administration and Finance portfolio, owns items 7 and 14. Faculty contribute only their own certified true copy transcripts and signed contracts - and here ALL faculty, part-time included, must supply documents, because checklist item 5.1 covers the whole roster.
A83: G. PROGRESS ROLL-UP (updates itself from the Tracker)
A84: Total requirements | B84: =COUNT(Tracker!$A$5:$A$90)
A85: Not started | B85: =COUNTIF(Tracker!$G$5:$G$90,"Not started")
A86: In progress | B86: =COUNTIF(Tracker!$G$5:$G$90,"In progress")
A87: For review | B87: =COUNTIF(Tracker!$G$5:$G$90,"For review")
A88: Done | B88: =COUNTIF(Tracker!$G$5:$G$90,"Done")
A89: Overall completion | B89: =IFERROR(AVERAGE(Tracker!$H$5:$H$90),0)
A90: Items overdue today | B90: =COUNTIFS(Tracker!$F$5:$F$90,"<"&TODAY(),Tracker!$G$5:$G$90,"<>Done")
A91: Items due within 7 days | B91: =COUNTIFS(Tracker!$F$5:$F$90,">="&TODAY(),Tracker!$F$5:$F$90,"<="&TODAY()+7,Tracker!$G$5:$G$90,"<>Done")
A92: Faculty on the roster | B92: =COUNTA(Faculty!$B$5:$B$59)
A93: Full-time faculty tasked | B93: =COUNTIF(Faculty!$E$5:$E$59,"FT")
A94: Part-time faculty not tasked | B94: =COUNTIF(Faculty!$E$5:$E$59,"PT")
A95: Days to the 13 Nov 2026 filing target | B95: =DATE(2026,11,13)-TODAY()
A97: H. HOW TO USE THIS WORKBOOK
A98: Yellow cells | B98: On the Tracker, only the Status, % and Notes columns are yours to edit. Everything else is fixed so the roll-ups stay reliable.
A99: Status | B99: Pick from the drop-down only: Not started, In progress, For review, Done. Anything else is rejected, because the counts above depend on these exact words.
A100: Colours on the Tracker | B100: A row shaded orange is past its due date and not yet Done. A row shaded amber is due within seven days. Green in the Status column means Done.
A101: Filtering | B101: Row 4 on the Tracker, Assignments and Faculty sheets has filters. A Program Chair can filter the Owner column to their own name and see only their items; a faculty member can find their own row on the Faculty sheet.
A102: One owner per item | B102: Every one of the 80 items has exactly one accountable owner. Faculty and committees are support — they contribute the work, but the named owner answers for delivery. All five working bodies have a named lead: the eight Curriculum & Syllabi Committees (each Programme Chair), the Library Collection Committee (Pastrana), the Feasibility & Market Study Committee (Francisco) and the two college-wide pools (K. Garcia and Castillo). Since 13 September 2026 every full-time faculty member also carries a named specific task in the Specific task assigned column of the Faculty sheet — the 12 pool writers by course, the other 15 as a counted task pending their Chair's allocation under items 76 to 80.

Sheet Faculty
A1: FACULTY — COMMITTEE ASSIGNMENTS
A2: Complete roster, First Semester AY 2026–2027 (55 faculty; 34 full-time, 21 part-time). The full list is kept because checklist item 5.1 requires every faculty member in general education and major courses. Only full-time faculty are tasked. Current load is shown so Chairs can allocate drafting fairly.
A4: # | B4: Faculty name | C4: Credential | D4: Department | E4: FT / PT | F4: Units this sem. | G4: Preps | H4: Committee assignment | I4: Specific task assigned | J4: Tracker items supporting | K4: Notes
A5: 1 | B5: Cruel, Ken Gie Anthony | C5: CPA | D5: BSA & BSAIS (Accountancy / AIS) | E5: FT | F5: 12 | G5: 4 | H5: Curriculum & Syllabi — BSA/BSAIS | I5: PROGRAM CHAIR (BSA and BSAIS) and VICE DEAN — owns tracker items 2, 3, 15 to 26, 71 and 72. Sole full-time author of the roughly 41 programme-specialised accountancy and AIS course descriptions and syllabi (Open Item 9); the 20 general education courses and the 13 shared business courses are lifted off this load by the two college-wide pools. Also runs the compliance audit of all eight programmes' curriculum submissions. Descriptions 9 Oct 2026, syllabi 16 Oct 2026. Records obligation on top, compulsory for all faculty: certified true copy of Transcript of Records and signed contract to HR by 30 Oct 2026 (items 12–13). PROPOSED FIRST YEAR TRIMESTER LOADING — teaches AE11-ECO1 Managerial Economics (T1), AE15-IA1 Intermediate Accounting 1 (T2), AE22-CAC Cost Accounting and Control (T3). Writes the course description and the outcomes-based syllabus for each of those courses, for review by the Program Chair. | J5: #19–20, 25–26 | K5: Listed in the leadership block of the Assignment Matrix as Vice Dean Ken Gie Anthony G. Cruel.
A6: 2 | B6: Carasco, Ryan Jay | C6: CPA | D6: BSA & BSAIS (Accountancy / AIS) | E6: PT | F6: 6 | G6: 2 | H6: Not tasked — part-time | I6: Not tasked with project work (part-time). Records obligation only, and it is compulsory: submit your certified true copy of Transcript of Records and your signed appointment / contract / letter of commitment to HR Officer Dela Cruz by 30 Oct 2026 — checklist items 5.2 and 5.3, tracker items 12 and 13. | J6: — | K6: Part-time. Not named in the First Year trimester loading — task him when the Second and Third Year loadings are drawn.
A7: 3 | B7: Cruz, Rommel | C7: CPA | D7: BSA & BSAIS (Accountancy / AIS) | E7: PT | F7: 6 | G7: 2 | H7: Curriculum & Syllabi — BSA/BSAIS professional courses | I7: PROPOSED FIRST YEAR TRIMESTER LOADING — teaches AE19-FINMGT Financial Management (T3). Writes the course description and the outcomes-based syllabus for each of those courses, for review by the Program Chair. | J7: #19–20, 25–26 | K7: Part-time, but named in the Proposed Faculty Loading, so tasked with the courses that loading gives them.
A8: 4 | B8: Empay, Jan Rhommer | C8: CPA | D8: BSA & BSAIS (Accountancy / AIS) | E8: PT | F8: 9 | G8: 3 | H8: Curriculum & Syllabi — BSA/BSAIS professional courses | I8: PROPOSED FIRST YEAR TRIMESTER LOADING — teaches CBME 1 Operations Management and TQM (T1), AE1-BL1 Law on Obligations and Contracts (T3). Writes the course description and the outcomes-based syllabus for each of those courses, for review by the Program Chair. | J8: #19–20, 25–26 | K8: Part-time, but named in the Proposed Faculty Loading, so tasked with the courses that loading gives them.
A9: 5 | B9: Francisco, Josephine Rose | C9: CPA | D9: BSA & BSAIS (Accountancy / AIS) | E9: PT | F9: 9 | G9: 3 | H9: Curriculum & Syllabi — BSA/BSAIS professional courses | I9: PROPOSED FIRST YEAR TRIMESTER LOADING — teaches AE13-FAR Financial Accounting and Reporting (T1), AE14-CFAS Conceptual Framework and Accounting Standards (T2). Writes the course description and the outcomes-based syllabus for each of those courses, for review by the Program Chair. | J9: #19–20, 25–26 | K9: Part-time, but named in the Proposed Faculty Loading, so tasked with the courses that loading gives them.
A10: 6 | B10: Santiago, Decirae Nicole | C10: CPA | D10: BSA & BSAIS (Accountancy / AIS) | E10: PT | F10: 6 | G10: 2 | H10: Curriculum & Syllabi — BSA/BSAIS professional courses | I10: PROPOSED FIRST YEAR TRIMESTER LOADING — teaches AE4-MGT1 Management Science (T3). Writes the course description and the outcomes-based syllabus for each of those courses, for review by the Program Chair. | J10: #19–20, 25–26 | K10: Part-time, but named in the Proposed Faculty Loading, so tasked with the courses that loading gives them.
A11: 7 | B11: Aquino, Ann Jellie B. | D11: BSBA (Business Administration) | E11: FT | F11: 24 | G11: 6 | H11: Curriculum & Syllabi — BSBA; Business Cluster Pool (BSA/BSAIS/BSBA/BSHM); Feasibility & Market Study | I11: BUSINESS CLUSTER POOL (tracker item 75) — write the COURSE DESCRIPTION and the OBE SYLLABUS for 3 allocated courses, one set serving BSA, BSAIS, BSBA and BSHM: AE11-ECO1 Managerial Economics; AE12-ECO2 Economic Development; AE5-IBT International Business and Trade. 6 documents in total. Common syllabus template: 14-week trimester, 56 hours per 3-unit course, two examinations (midterm and final) plus one required monthly assessment and regular quizzes. Hand in to Chair Ranilo S. Castillo II: descriptions 9 Oct 2026, syllabi 16 Oct 2026. CANDIDATE LIST — these 13 shared courses were read off the BSA and BSAIS prospectus; Chair Ranilo S. Castillo II confirms them against the BSBA and BSHM prospectuses under item 75 before writing starts. Also carries a share of the BSBA programme-specialised courses under item 80. Also sits on the Feasibility & Market Study Committee (items 4 to 6). Records obligation on top, compulsory for all faculty: certified true copy of Transcript of Records and signed contract to HR by 30 Oct 2026 (items 12–13). | J11: #4–6, 19–20, 25–26, 31–32, 43–44
A12: 8 | B12: Bauat, Jhosalyn | D12: BSBA (Business Administration) | E12: FT | F12: 24 | G12: 6 | H12: Curriculum & Syllabi — BSBA; Business Cluster Pool (BSA/BSAIS/BSBA/BSHM) | I12: BUSINESS CLUSTER POOL (tracker item 75) — write the COURSE DESCRIPTION and the OBE SYLLABUS for 4 allocated courses, one set serving BSA, BSAIS, BSBA and BSHM: CBME 1 Operations Management and TQM; CBME 2 Strategic Management; AE4-MGT1 Management Science; PE1-HBO Human Behavior in Organizations. 8 documents in total. Common syllabus template: 14-week trimester, 56 hours per 3-unit course, two examinations (midterm and final) plus one required monthly assessment and regular quizzes. Hand in to Chair Ranilo S. Castillo II: descriptions 9 Oct 2026, syllabi 16 Oct 2026. CANDIDATE LIST — these 13 shared courses were read off the BSA and BSAIS prospectus; Chair Ranilo S. Castillo II confirms them against the BSBA and BSHM prospectuses under item 75 before writing starts. Also carries a share of the BSBA programme-specialised courses under item 80. Takes the fourth course because she is the only pool writer on no third committee. Records obligation on top, compulsory for all faculty: certified true copy of Transcript of Records and signed contract to HR by 30 Oct 2026 (items 12–13). | J12: #19–20, 25–26, 31–32, 43–44
A13: 9 | B13: Castillo, Ranilo S. | D13: BSBA (Business Administration) | E13: FT | F13: 12 | G13: 2 | H13: Curriculum & Syllabi — BSBA | I13: PROGRAM CHAIR (BSBA) and LEAD of the Business Cluster Pool — owns items 27 to 32, 75 and 80. As pool lead: fix the definitive shared-course list (confirm the 13 candidate courses against the BSBA and BSHM prospectuses), publish the writer allocation, issue the common template carrying the assessment scheme and the 14-week / 56-hour basis, set internal hand-in dates ahead of 9 Oct and 16 Oct, hand one finished set to the Chairs of BSA, BSAIS and BSHM, and report slippage to the Vice Dean. Publish the item 80 BSBA specialised allocation at the same time so each writer's total is visible. Records obligation on top, compulsory for all faculty: certified true copy of Transcript of Records and signed contract to HR by 30 Oct 2026 (items 12–13). | J13: #31–32 | K13: Listed in the leadership block of the Assignment Matrix as Program Chair Ranilo S. Castillo II.
A14: 10 | B14: Dela Cruz, Jacqueline | D14: BSBA (Business Administration) | E14: FT | F14: 24 | G14: 5 | H14: Curriculum & Syllabi — BSBA; Business Cluster Pool (BSA/BSAIS/BSBA/BSHM); Library Collection | I14: BUSINESS CLUSTER POOL (tracker item 75) — write the COURSE DESCRIPTION and the OBE SYLLABUS for 3 allocated courses, one set serving BSA, BSAIS, BSBA and BSHM: AE19-FINMGT Financial Management; AE18-FINMKT Financial Markets; AE10-GOV Governance, Business Ethics, Risk Management and Internal Control. 6 documents in total. Common syllabus template: 14-week trimester, 56 hours per 3-unit course, two examinations (midterm and final) plus one required monthly assessment and regular quizzes. Hand in to Chair Ranilo S. Castillo II: descriptions 9 Oct 2026, syllabi 16 Oct 2026. CANDIDATE LIST — these 13 shared courses were read off the BSA and BSAIS prospectus; Chair Ranilo S. Castillo II confirms them against the BSBA and BSHM prospectuses under item 75 before writing starts. Also carries a share of the BSBA programme-specialised courses under item 80. Held to three courses because she also sits on the Library Collection Committee (items 66 and 67). Records obligation on top, compulsory for all faculty: certified true copy of Transcript of Records and signed contract to HR by 30 Oct 2026 (items 12–13). | J14: #19–20, 25–26, 31–32, 43–44, 66–67
A15: 11 | B15: Salas, Kristine Joy | D15: BSBA (Business Administration) | E15: FT | F15: 24 | G15: 6 | H15: Curriculum & Syllabi — BSBA; Business Cluster Pool (BSA/BSAIS/BSBA/BSHM) | I15: BUSINESS CLUSTER POOL (tracker item 75) — write the COURSE DESCRIPTION and the OBE SYLLABUS for 3 allocated courses, one set serving BSA, BSAIS, BSBA and BSHM: AE1-BL1 Law on Obligations and Contracts; AE2-BL2 Business Laws and Regulations; AE3-BL3 Regulatory Framework and Legal Issues in Business. 6 documents in total. Common syllabus template: 14-week trimester, 56 hours per 3-unit course, two examinations (midterm and final) plus one required monthly assessment and regular quizzes. Hand in to Chair Ranilo S. Castillo II: descriptions 9 Oct 2026, syllabi 16 Oct 2026. CANDIDATE LIST — these 13 shared courses were read off the BSA and BSAIS prospectus; Chair Ranilo S. Castillo II confirms them against the BSBA and BSHM prospectuses under item 75 before writing starts. Also carries a share of the BSBA programme-specialised courses under item 80. Records obligation on top, compulsory for all faculty: certified true copy of Transcript of Records and signed contract to HR by 30 Oct 2026 (items 12–13). | J15: #19–20, 25–26, 31–32, 43–44
A16: 12 | B16: Patiag, Glaiza Kaye | C16: JD | D16: BSBA (Business Administration) & BS Hospitality Management | E16: PT | F16: 9 | G16: 2 | H16: Not tasked — part-time | I16: Not tasked with project work (part-time). Records obligation only, and it is compulsory: submit your certified true copy of Transcript of Records and your signed appointment / contract / letter of commitment to HR Officer Dela Cruz by 30 Oct 2026 — checklist items 5.2 and 5.3, tracker items 12 and 13. | J16: — | K16: Teaches in two departments; counted once. Part-time — not tasked.
A17: 13 | B17: Arimbuyutan, Jazzele M. | D17: BS Criminology | E17: FT | F17: 21 | G17: 4 | H17: Curriculum & Syllabi — BSCRIM; Feasibility & Market Study | I17: PROGRAMME-SPECIALISED COURSES — BSCRIM. Write the COURSE DESCRIPTION and the OBE SYLLABUS for the BSCRIM major courses allocated to you by Chair Pisto. The allocation naming your specific courses is tracked as item 76, due 25 Sep 2026. Common syllabus template: 14-week trimester, 56 hours per 3-unit course, two examinations (midterm and final) plus one required monthly assessment and regular quizzes. Hand in to your Chair: descriptions 9 Oct 2026, syllabi 16 Oct 2026. Feeds tracker items 49 and 50. Also sits on the Feasibility & Market Study Committee (items 4 to 6). Records obligation on top, compulsory for all faculty: certified true copy of Transcript of Records and signed contract to HR by 30 Oct 2026 (items 12–13). | J17: #4–6, 49–50
A18: 14 | B18: Dela Cruz, Jhon Allen R. | D18: BS Criminology | E18: FT | F18: 22 | G18: 5 | H18: Curriculum & Syllabi — BSCRIM | I18: PROGRAMME-SPECIALISED COURSES — BSCRIM. Write the COURSE DESCRIPTION and the OBE SYLLABUS for the BSCRIM major courses allocated to you by Chair Pisto. The allocation naming your specific courses is tracked as item 76, due 25 Sep 2026. Common syllabus template: 14-week trimester, 56 hours per 3-unit course, two examinations (midterm and final) plus one required monthly assessment and regular quizzes. Hand in to your Chair: descriptions 9 Oct 2026, syllabi 16 Oct 2026. Feeds tracker items 49 and 50. Records obligation on top, compulsory for all faculty: certified true copy of Transcript of Records and signed contract to HR by 30 Oct 2026 (items 12–13). | J18: #49–50
A19: 15 | B19: Diaz, Pamela B. | D19: BS Criminology | E19: FT | F19: 22 | G19: 5 | H19: Curriculum & Syllabi — BSCRIM | I19: PROGRAMME-SPECIALISED COURSES — BSCRIM. Write the COURSE DESCRIPTION and the OBE SYLLABUS for the BSCRIM major courses allocated to you by Chair Pisto. The allocation naming your specific courses is tracked as item 76, due 25 Sep 2026. Common syllabus template: 14-week trimester, 56 hours per 3-unit course, two examinations (midterm and final) plus one required monthly assessment and regular quizzes. Hand in to your Chair: descriptions 9 Oct 2026, syllabi 16 Oct 2026. Feeds tracker items 49 and 50. Records obligation on top, compulsory for all faculty: certified true copy of Transcript of Records and signed contract to HR by 30 Oct 2026 (items 12–13). | J19: #49–50
A20: 16 | B20: Pamiloza, Honey Mica R. | D20: BS Criminology | E20: FT | F20: 21 | G20: 4 | H20: Curriculum & Syllabi — BSCRIM | I20: PROGRAMME-SPECIALISED COURSES — BSCRIM. Write the COURSE DESCRIPTION and the OBE SYLLABUS for the BSCRIM major courses allocated to you by Chair Pisto. The allocation naming your specific courses is tracked as item 76, due 25 Sep 2026. Common syllabus template: 14-week trimester, 56 hours per 3-unit course, two examinations (midterm and final) plus one required monthly assessment and regular quizzes. Hand in to your Chair: descriptions 9 Oct 2026, syllabi 16 Oct 2026. Feeds tracker items 49 and 50. Records obligation on top, compulsory for all faculty: certified true copy of Transcript of Records and signed contract to HR by 30 Oct 2026 (items 12–13). | J20: #49–50
A21: 17 | B21: Pisto, Samantha Rose C. | D21: BS Criminology | E21: FT | F21: 6 | G21: 2 | H21: Curriculum & Syllabi — BSCRIM | I21: PROGRAM CHAIR (BSCRIM) — owns items 45 to 50 and 76. Publish the BSCRIM writer allocation by 25 Sep 2026 naming which of your five full-time faculty writes which major course, then collect descriptions 9 Oct and syllabi 16 Oct. Outstanding defect on item 45: the two 25-unit trimesters put students at 8.33 contact hours a day and need re-sequencing. Records obligation on top, compulsory for all faculty: certified true copy of Transcript of Records and signed contract to HR by 30 Oct 2026 (items 12–13). | J21: #49–50 | K21: Listed in the leadership block of the Assignment Matrix as Program Chair Samantha Rose C. Pisto.
A22: 18 | B22: Ramos, Leandro M. | D22: BS Criminology | E22: FT | F22: 18 | G22: 4 | H22: Curriculum & Syllabi — BSCRIM; Library Collection | I22: PROGRAMME-SPECIALISED COURSES — BSCRIM. Write the COURSE DESCRIPTION and the OBE SYLLABUS for the BSCRIM major courses allocated to you by Chair Pisto. The allocation naming your specific courses is tracked as item 76, due 25 Sep 2026. Common syllabus template: 14-week trimester, 56 hours per 3-unit course, two examinations (midterm and final) plus one required monthly assessment and regular quizzes. Hand in to your Chair: descriptions 9 Oct 2026, syllabi 16 Oct 2026. Feeds tracker items 49 and 50. Also on the Library Collection Committee — supply BSCRIM subject title lists and accession data for items 66 and 67. Records obligation on top, compulsory for all faculty: certified true copy of Transcript of Records and signed contract to HR by 30 Oct 2026 (items 12–13). PROPOSED FIRST YEAR TRIMESTER LOADING — teaches NSTP 1 (T1) and NSTP 2 (T2), Civic Welfare Training Service. Writes the course description and the outcomes-based syllabus for each of those courses, for review by the Program Chair. | J22: #49–50, 66–67, #19–20, 25–26
A23: 19 | B23: Timpac, Theodore M. | C23: Atty. | D23: BS Criminology | E23: PT | F23: 12 | G23: 2 | H23: Not tasked — part-time | I23: Not tasked with project work (part-time). Records obligation only, and it is compulsory: submit your certified true copy of Transcript of Records and your signed appointment / contract / letter of commitment to HR Officer Dela Cruz by 30 Oct 2026 — checklist items 5.2 and 5.3, tracker items 12 and 13. | J23: — | K23: Part-time — not tasked.
A24: 20 | B24: Cristobal, Teofilo G. | D24: BS Computer Science | E24: FT | F24: 24 | G24: 3 | H24: Curriculum & Syllabi — BSCS | I24: PROGRAMME-SPECIALISED COURSES — BSCS. Write the COURSE DESCRIPTION and the OBE SYLLABUS for the BSCS major courses allocated to you by Chair Diamat. The allocation naming your specific courses is tracked as item 78, due 25 Sep 2026. Common syllabus template: 14-week trimester, 56 hours per 3-unit course, two examinations (midterm and final) plus one required monthly assessment and regular quizzes. Hand in to your Chair: descriptions 9 Oct 2026, syllabi 16 Oct 2026. Feeds tracker items 37 and 38. CAPACITY: you are the only full-time BSCS faculty besides the Chair, so item 78 must state which courses fall to the Chair himself. Also confirm your department is corrected to BS Computer Science on the roster main sheet before filing. Records obligation on top, compulsory for all faculty: certified true copy of Transcript of Records and signed contract to HR by 30 Oct 2026 (items 12–13). | J24: #37–38 | K24: Confirmed by the Vice Dean as full-time in BSCS, not Teacher Education. The roster main sheet lists him under Teacher Education — correct that before the dossier is filed.
A25: 21 | B25: Diamat, John Philip N. | D25: BS Computer Science | E25: FT | F25: 9 | G25: 3 | H25: Curriculum & Syllabi — BSCS | I25: PROGRAM CHAIR (BSCS) — owns items 33 to 38 and 78. Publish the BSCS writer allocation by 25 Sep 2026. With only one full-time writer besides yourself, that allocation must say plainly which courses you take and where outside help is needed — the same shape of problem as Open Item 9. Records obligation on top, compulsory for all faculty: certified true copy of Transcript of Records and signed contract to HR by 30 Oct 2026 (items 12–13). | J25: #37–38 | K25: Listed in the leadership block of the Assignment Matrix as Program Chair John Philip N. Diamat.
A26: 22 | B26: Corpuz, Alpha Jessa | D26: BS Computer Science | E26: PT | F26: 3 | G26: 1 | H26: Not tasked — part-time | I26: Not tasked with project work (part-time). Records obligation only, and it is compulsory: submit your certified true copy of Transcript of Records and your signed appointment / contract / letter of commitment to HR Officer Dela Cruz by 30 Oct 2026 — checklist items 5.2 and 5.3, tracker items 12 and 13. | J26: — | K26: Part-time — not tasked.
A27: 23 | B27: Fernando, Eddyson S. | D27: BS Computer Science | E27: PT | F27: 9 | G27: 3 | H27: Not tasked — part-time | I27: Not tasked with project work (part-time). Records obligation only, and it is compulsory: submit your certified true copy of Transcript of Records and your signed appointment / contract / letter of commitment to HR Officer Dela Cruz by 30 Oct 2026 — checklist items 5.2 and 5.3, tracker items 12 and 13. | J27: — | K27: Part-time — not tasked.
A28: 24 | B28: Francisco, Jayson R. | D28: BS Computer Science | E28: PT | F28: 3 | G28: 1 | H28: Not tasked — part-time | I28: MIS HEAD and TASK FORCE CO-LEAD — owns items 1, 4, 5, 6, 70 and 73. Item 73 is the single written request to CHED Region III covering Open Items 2 to 5, due 25 Sep 2026; Open Item 5 (are syllabi needed for every course or only new and re-sequenced ones) governs the whole 16 Oct syllabus deadline. Not allocated course-writing — part-time teaching load. Submit your certified true copy of transcript of records and your signed appointment / contract / letter of commitment to hr officer dela cruz by 30 oct 2026 — checklist items 5.2 and 5.3, tracker items 12 and 13. | J28: — | K28: Listed in the leadership block of the Assignment Matrix as MIS Head Jayson R. Francisco. Part-time — not tasked.
A29: 25 | B29: Garcia, Michael Johnrein | D29: BS Computer Science | E29: PT | F29: 9 | G29: 3 | H29: Not tasked — part-time | I29: Not tasked with project work (part-time). Records obligation only, and it is compulsory: submit your certified true copy of Transcript of Records and your signed appointment / contract / letter of commitment to HR Officer Dela Cruz by 30 Oct 2026 — checklist items 5.2 and 5.3, tracker items 12 and 13. | J29: — | K29: Part-time — not tasked.
A30: 26 | B30: Peralta, Ronel Evan P. | D30: BS Computer Science | E30: PT | F30: 9 | G30: 3 | H30: Not tasked — part-time | I30: Not tasked with project work (part-time). Records obligation only, and it is compulsory: submit your certified true copy of Transcript of Records and your signed appointment / contract / letter of commitment to HR Officer Dela Cruz by 30 Oct 2026 — checklist items 5.2 and 5.3, tracker items 12 and 13. | J30: — | K30: Part-time — not tasked.
A31: 27 | B31: Bernardo, Romeo DG | D31: BS Hospitality Management | E31: FT | F31: 21 | G31: 4 | H31: Curriculum & Syllabi — BSHM; Library Collection | I31: PROGRAMME-SPECIALISED COURSES — BSHM. Write the COURSE DESCRIPTION and the OBE SYLLABUS for the BSHM major courses allocated to you by Chair Ciasico. The allocation naming your specific courses is tracked as item 77, due 25 Sep 2026. Common syllabus template: 14-week trimester, 56 hours per 3-unit course, two examinations (midterm and final) plus one required monthly assessment and regular quizzes. Hand in to your Chair: descriptions 9 Oct 2026, syllabi 16 Oct 2026. Feeds tracker items 43 and 44. Also a named member of the library team — owns the working papers behind items 66 to 69 with Sta. Cruz, on top of a 21-unit teaching load. Weight your course share accordingly with the Chair. Records obligation on top, compulsory for all faculty: certified true copy of Transcript of Records and signed contract to HR by 30 Oct 2026 (items 12–13). | J31: #43–44, 66–69 | K31: Also a member of the library team named in the project plan — library duty on top of a full teaching load.
A32: 28 | B32: Ciasico, Stephanie S. | D32: BS Hospitality Management | E32: FT | F32: 9 | G32: 2 | H32: Curriculum & Syllabi — BSHM | I32: PROGRAM CHAIR (BSHM) — owns items 39 to 44 and 77. Publish the BSHM writer allocation by 25 Sep 2026. Only hospitality-specialised courses need allocating: the shared business courses come from the Business Cluster Pool under item 75. Bernardo carries library items 66 to 69 as well — weight his share. Records obligation on top, compulsory for all faculty: certified true copy of Transcript of Records and signed contract to HR by 30 Oct 2026 (items 12–13). | J32: #43–44 | K32: Listed in the leadership block of the Assignment Matrix as Program Chair Stephanie S. Ciasico.
A33: 29 | B33: Dela Cruz, Jonathan | D33: BS Hospitality Management | E33: FT | F33: 18 | G33: 4 | H33: Curriculum & Syllabi — BSHM; Feasibility & Market Study | I33: PROGRAMME-SPECIALISED COURSES — BSHM. Write the COURSE DESCRIPTION and the OBE SYLLABUS for the BSHM major courses allocated to you by Chair Ciasico. The allocation naming your specific courses is tracked as item 77, due 25 Sep 2026. Common syllabus template: 14-week trimester, 56 hours per 3-unit course, two examinations (midterm and final) plus one required monthly assessment and regular quizzes. Hand in to your Chair: descriptions 9 Oct 2026, syllabi 16 Oct 2026. Feeds tracker items 43 and 44. Also sits on the Feasibility & Market Study Committee (items 4 to 6). Records obligation on top, compulsory for all faculty: certified true copy of Transcript of Records and signed contract to HR by 30 Oct 2026 (items 12–13). | J33: #4–6, 43–44
A34: 30 | B34: Geronimo, Jing Feng A. | C34: LPT | D34: BS Hospitality Management | E34: FT | F34: 24 | G34: 4 | H34: Curriculum & Syllabi — BSHM | I34: PROGRAMME-SPECIALISED COURSES — BSHM. Write the COURSE DESCRIPTION and the OBE SYLLABUS for the BSHM major courses allocated to you by Chair Ciasico. The allocation naming your specific courses is tracked as item 77, due 25 Sep 2026. Common syllabus template: 14-week trimester, 56 hours per 3-unit course, two examinations (midterm and final) plus one required monthly assessment and regular quizzes. Hand in to your Chair: descriptions 9 Oct 2026, syllabi 16 Oct 2026. Feeds tracker items 43 and 44. Carries the courses of Franco, Nadine Denise, who resigned — make sure the roster HR locks on 23 Oct 2026 shows you, not her. Records obligation on top, compulsory for all faculty: certified true copy of Transcript of Records and signed contract to HR by 30 Oct 2026 (items 12–13). | J34: #43–44 | K34: Replaced Franco, Nadine Denise, who resigned (3 Sep 2026). Continues the same teaching load and courses. Update the roster at source before HR locks the faculty spreadsheet on 23 October.
A35: 31 | B35: Aberin, Gabriel Angelo | D35: BS Hospitality Management | E35: PT | F35: 9 | G35: 2 | H35: Not tasked — part-time | I35: Not tasked with project work (part-time). Records obligation only, and it is compulsory: submit your certified true copy of Transcript of Records and your signed appointment / contract / letter of commitment to HR Officer Dela Cruz by 30 Oct 2026 — checklist items 5.2 and 5.3, tracker items 12 and 13. | J35: — | K35: Part-time — not tasked.
A36: 32 | B36: Alarcon, Leuz Rafael | D36: BS Hospitality Management | E36: PT | F36: 9 | G36: 2 | H36: Not tasked — part-time | I36: Not tasked with project work (part-time). Records obligation only, and it is compulsory: submit your certified true copy of Transcript of Records and your signed appointment / contract / letter of commitment to HR Officer Dela Cruz by 30 Oct 2026 — checklist items 5.2 and 5.3, tracker items 12 and 13. | J36: — | K36: Part-time — not tasked.
A37: 33 | B37: Mariano, Jerick | D37: BS Hospitality Management | E37: PT | F37: 9 | G37: 2 | H37: Not tasked — part-time | I37: Not tasked with project work (part-time). Records obligation only, and it is compulsory: submit your certified true copy of Transcript of Records and your signed appointment / contract / letter of commitment to HR Officer Dela Cruz by 30 Oct 2026 — checklist items 5.2 and 5.3, tracker items 12 and 13. | J37: — | K37: Part-time — not tasked.
A38: 34 | B38: Patiag, Mark | C38: Atty. | D38: BS Hospitality Management | E38: PT | F38: 3 | G38: 1 | H38: Not tasked — part-time | I38: Not tasked with project work (part-time). Records obligation only, and it is compulsory: submit your certified true copy of Transcript of Records and your signed appointment / contract / letter of commitment to HR Officer Dela Cruz by 30 Oct 2026 — checklist items 5.2 and 5.3, tracker items 12 and 13. | J38: — | K38: Part-time — not tasked.
A39: 35 | B39: Santos, John Vincent L. | C39: Engr. | D39: BS Hospitality Management | E39: PT | F39: 6 | G39: 2 | H39: Not tasked — part-time | I39: Not tasked with project work (part-time). Records obligation only, and it is compulsory: submit your certified true copy of Transcript of Records and your signed appointment / contract / letter of commitment to HR Officer Dela Cruz by 30 Oct 2026 — checklist items 5.2 and 5.3, tracker items 12 and 13. | J39: — | K39: Part-time — not tasked.
A40: 36 | B40: Ablaya, Stephanie | D40: Teacher Education (BEED / BSEDE / BSEDM / TEP) | E40: FT | F40: 27 | G40: 6 | H40: Curriculum & Syllabi — BEED/BSED; Feasibility & Market Study | I40: PROGRAMME-SPECIALISED COURSES — BEED and BSED. Write the COURSE DESCRIPTION and the OBE SYLLABUS for the BEED and BSED major courses allocated to you by Chair K. Garcia. The allocation naming your specific courses is tracked as item 79, due 25 Sep 2026. Common syllabus template: 14-week trimester, 56 hours per 3-unit course, two examinations (midterm and final) plus one required monthly assessment and regular quizzes. Hand in to your Chair: descriptions 9 Oct 2026, syllabi 16 Oct 2026. Feeds tracker items 55 and 56 (BEED) and 61 and 62 (BSED). Also sits on the Feasibility & Market Study Committee (items 4 to 6). Records obligation on top, compulsory for all faculty: certified true copy of Transcript of Records and signed contract to HR by 30 Oct 2026 (items 12–13). | J40: #4–6, 55–56, 61–62
A41: 37 | B41: Aquino, Agnes M. | C41: Dr. | D41: Teacher Education (BEED / BSEDE / BSEDM / TEP) | E41: FT | F41: 24 | G41: 7 | H41: Curriculum & Syllabi — BEED/BSED | I41: PROGRAMME-SPECIALISED COURSES — BEED and BSED. Write the COURSE DESCRIPTION and the OBE SYLLABUS for the BEED and BSED major courses allocated to you by Chair K. Garcia. The allocation naming your specific courses is tracked as item 79, due 25 Sep 2026. Common syllabus template: 14-week trimester, 56 hours per 3-unit course, two examinations (midterm and final) plus one required monthly assessment and regular quizzes. Hand in to your Chair: descriptions 9 Oct 2026, syllabi 16 Oct 2026. Feeds tracker items 55 and 56 (BEED) and 61 and 62 (BSED). MOVED OUT OF THE GENERAL EDUCATION SYLLABI POOL on 13 Sep 2026 by direction of the Vice Dean, so that this major-course load is not carried on top of the college-wide general education work — you hold the heaviest prep count in the department at 7. Records obligation on top, compulsory for all faculty: certified true copy of Transcript of Records and signed contract to HR by 30 Oct 2026 (items 12–13). | J41: #55–56, 61–62, 79 | K41: Moved out of the General Education Syllabi Pool 13 Sep 2026 by direction of the Vice Dean — she writes BEED/BSED major courses instead. The pool now has 7 writers.
A42: 38 | B42: Cajucom, Ryan Neil | D42: Teacher Education (BEED / BSEDE / BSEDM / TEP) | E42: FT | F42: 27 | G42: 6 | H42: Curriculum & Syllabi — BEED/BSED | I42: PROGRAMME-SPECIALISED COURSES — BEED and BSED. Write the COURSE DESCRIPTION and the OBE SYLLABUS for the BEED and BSED major courses allocated to you by Chair K. Garcia. The allocation naming your specific courses is tracked as item 79, due 25 Sep 2026. Common syllabus template: 14-week trimester, 56 hours per 3-unit course, two examinations (midterm and final) plus one required monthly assessment and regular quizzes. Hand in to your Chair: descriptions 9 Oct 2026, syllabi 16 Oct 2026. Feeds tracker items 55 and 56 (BEED) and 61 and 62 (BSED). Records obligation on top, compulsory for all faculty: certified true copy of Transcript of Records and signed contract to HR by 30 Oct 2026 (items 12–13). | J42: #55–56, 61–62
A43: 39 | B43: Calma, Shiela Mae C. | D43: Teacher Education (BEED / BSEDE / BSEDM / TEP) | E43: FT | F43: 24 | G43: 4 | H43: Curriculum & Syllabi — BEED/BSED; General Education Syllabi Pool (college-wide) | I43: GENERAL EDUCATION SYLLABI POOL (tracker item 74) — write the COURSE DESCRIPTION and the OBE SYLLABUS for 3 allocated courses, one set serving all 8 programmes: PATH-FIT 1 Movement Competency Training; PATH-FIT 2 Exercise-Based Fitness Activities; NSTP 1 Civic Welfare Training Service 1. 6 documents in total. Common syllabus template: 14-week trimester, 56 hours per 3-unit course, two examinations (midterm and final) plus one required monthly assessment and regular quizzes. Hand in to Chair Kent E. Garcia: descriptions 9 Oct 2026, syllabi 16 Oct 2026. Course codes are the BSA/BSAIS spellings — reconcile with your own programme's codes once Open Item 7 is closed. Not included in the BEED/BSED specialised allocation (item 79) while carrying this pool load. NSTP 1 is the prerequisite of NSTP 2 and the two are split between Calma and Mequiabas — agree the two syllabi between you so the sequence holds. Records obligation on top, compulsory for all faculty: certified true copy of Transcript of Records and signed contract to HR by 30 Oct 2026 (items 12–13). PROPOSED FIRST YEAR TRIMESTER LOADING — teaches PATH-FIT 1 Movement Competency Training (T1). Writes the course description and the outcomes-based syllabus for each of those courses, for review by the Program Chair. | J43: #19–20, 25–26, 31–32, 37–38, 43–44, 49–50, 55–56, 61–62
A44: 40 | B44: Delos Reyes, Diana Maris | D44: Teacher Education (BEED / BSEDE / BSEDM / TEP) | E44: FT | F44: 27 | G44: 7 | H44: Curriculum & Syllabi — BEED/BSED | I44: PROGRAMME-SPECIALISED COURSES — BEED and BSED. Write the COURSE DESCRIPTION and the OBE SYLLABUS for the BEED and BSED major courses allocated to you by Chair K. Garcia. The allocation naming your specific courses is tracked as item 79, due 25 Sep 2026. Common syllabus template: 14-week trimester, 56 hours per 3-unit course, two examinations (midterm and final) plus one required monthly assessment and regular quizzes. Hand in to your Chair: descriptions 9 Oct 2026, syllabi 16 Oct 2026. Feeds tracker items 55 and 56 (BEED) and 61 and 62 (BSED). Records obligation on top, compulsory for all faculty: certified true copy of Transcript of Records and signed contract to HR by 30 Oct 2026 (items 12–13). | J44: #55–56, 61–62
A45: 41 | B45: Garcia, Almario B. | C45: Dr. | D45: Teacher Education (BEED / BSEDE / BSEDM / TEP) | E45: FT | F45: 3 | G45: 1 | H45: Curriculum & Syllabi — BEED/BSED | I45: COLLEGE DEAN and TASK FORCE CO-LEAD — support role, not allocated course-writing. Reviews and signs every programme's curriculum in the sign-off chain (prepared by the Chair, reviewed by the Dean, approved by the VPAA) and gives the executive endorsement of the completed dossier, item 71, by 10 Nov 2026. Records obligation on top, compulsory for all faculty: certified true copy of Transcript of Records and signed contract to HR by 30 Oct 2026 (items 12–13). | J45: #55–56, 61–62 | K45: Listed in the leadership block of the Assignment Matrix as Dean Dr. Almario B. Garcia.
A46: 42 | B46: Garcia, Kent E. | D46: Teacher Education (BEED / BSEDE / BSEDM / TEP) | E46: FT | F46: 12 | G46: 4 | H46: Curriculum & Syllabi — BEED/BSED | I46: PROGRAM CHAIR (BEED and BSED) and LEAD of the General Education Syllabi Pool — owns items 51 to 62, 74 and 79. As pool lead: allocate the 20 general education, PATH-FIT, NSTP and CLE courses across the eight writers (allocation below), issue one common syllabus template carrying the assessment scheme and the 14-week / 56-hour basis, set internal hand-in dates ahead of 9 Oct and 16 Oct, hand one finished set to all eight Chairs, and report slippage to the Vice Dean. BLOCKED BY OPEN ITEM 7 — you cannot allocate courses whose codes, units and hour splits are not yet harmonised across the eight programmes; raise that first. Publish item 79 separately: the six Teacher Education faculty NOT in the pool write the BEED and BSED major courses. Records obligation on top, compulsory for all faculty: certified true copy of Transcript of Records and signed contract to HR by 30 Oct 2026 (items 12–13). | J46: #55–56, 61–62 | K46: Listed in the leadership block of the Assignment Matrix as Program Chair Kent E. Garcia.
A47: 43 | B47: Germino, Melanie | D47: Teacher Education (BEED / BSEDE / BSEDM / TEP) | E47: FT | F47: 27 | G47: 7 | H47: Curriculum & Syllabi — BEED/BSED; General Education Syllabi Pool | I47: PROGRAMME-SPECIALISED COURSES — BEED and BSED. Write the COURSE DESCRIPTION and the OBE SYLLABUS for the BEED and BSED major courses allocated to you by Chair K. Garcia. The allocation naming your specific courses is tracked as item 79, due 25 Sep 2026. Common syllabus template: 14-week trimester, 56 hours per 3-unit course, two examinations (midterm and final) plus one required monthly assessment and regular quizzes. Hand in to your Chair: descriptions 9 Oct 2026, syllabi 16 Oct 2026. Feeds tracker items 55 and 56 (BEED) and 61 and 62 (BSED). Records obligation on top, compulsory for all faculty: certified true copy of Transcript of Records and signed contract to HR by 30 Oct 2026 (items 12–13). PROPOSED FIRST YEAR TRIMESTER LOADING — teaches MAT-GEC Mathematics in the Modern World and HIS-GEC Readings in Philippine History (T1). Writes the course description and the outcomes-based syllabus for each of those courses, for review by the Program Chair. GENERAL EDUCATION SYLLABI POOL (tracker item 74) — writes the course description and the OBE syllabus for HIS-GEC Readings in Philippine History, reallocated from D. Maglalang on her resignation, 26 Oct 2026. | J47: #55–56, 61–62, #19–20, 25–26, 74
A48: 44 | B48: Ilag, Ferdinand T. | D48: Teacher Education (BEED / BSEDE / BSEDM / TEP) | E48: FT | F48: 21 | G48: 3 | H48: Curriculum & Syllabi — BEED/BSED; General Education Syllabi Pool (college-wide) | I48: GENERAL EDUCATION SYLLABI POOL (tracker item 74) — write the COURSE DESCRIPTION and the OBE SYLLABUS for 3 allocated courses, one set serving all 8 programmes: REL-GEC Religion, Religious Experience and Spirituality; CLE 1 Church and Salvation History; STS-GEC Science, Technology and Society. 6 documents in total. Common syllabus template: 14-week trimester, 56 hours per 3-unit course, two examinations (midterm and final) plus one required monthly assessment and regular quizzes. Hand in to Chair Kent E. Garcia: descriptions 9 Oct 2026, syllabi 16 Oct 2026. Course codes are the BSA/BSAIS spellings — reconcile with your own programme's codes once Open Item 7 is closed. Not included in the BEED/BSED specialised allocation (item 79) while carrying this pool load. Records obligation on top, compulsory for all faculty: certified true copy of Transcript of Records and signed contract to HR by 30 Oct 2026 (items 12–13). PROPOSED FIRST YEAR TRIMESTER LOADING — teaches REL-GEC Religion, Religious Experience and Spirituality (T2), CLE 1 Church and Salvation History (T3) — CLE 1 reassigned from D. Maglalang, resigned. Writes the course description and the outcomes-based syllabus for each of those courses, for review by the Program Chair. Also takes CLE 2 in the GE pool, reallocated from D. Maglalang, 26 Oct 2026. | J48: #19–20, 25–26, 31–32, 37–38, 43–44, 49–50, 55–56, 61–62
A49: 45 | B49: Jamlang, Jamie A. | D49: Teacher Education (BEED / BSEDE / BSEDM / TEP) | E49: FT | F49: 27 | G49: 5 | H49: Curriculum & Syllabi — BEED/BSED; General Education Syllabi Pool (college-wide) | I49: GENERAL EDUCATION SYLLABI POOL (tracker item 74) — write the COURSE DESCRIPTION and the OBE SYLLABUS for 2 allocated courses, one set serving all 8 programmes: CON-GEC The Contemporary World; ITE-GEC Living in the I.T. Era. 4 documents in total. Common syllabus template: 14-week trimester, 56 hours per 3-unit course, two examinations (midterm and final) plus one required monthly assessment and regular quizzes. Hand in to Chair Kent E. Garcia: descriptions 9 Oct 2026, syllabi 16 Oct 2026. Course codes are the BSA/BSAIS spellings — reconcile with your own programme's codes once Open Item 7 is closed. Not included in the BEED/BSED specialised allocation (item 79) while carrying this pool load. Records obligation on top, compulsory for all faculty: certified true copy of Transcript of Records and signed contract to HR by 30 Oct 2026 (items 12–13). PROPOSED FIRST YEAR TRIMESTER LOADING — teaches RIZ-GEC The Life and Works of Rizal (T3). Writes the course description and the outcomes-based syllabus for each of those courses, for review by the Program Chair. Also takes RIZ-GEC in the GE pool, reallocated from D. Maglalang, 26 Oct 2026. | J49: #19–20, 25–26, 31–32, 37–38, 43–44, 49–50, 55–56, 61–62
A50: 46 | B50: Manuel, Consuelo V. | C50: Dr. | D50: Teacher Education (BEED / BSEDE / BSEDM / TEP) | E50: FT | F50: 24 | G50: 4 | H50: Curriculum & Syllabi — BEED/BSED; General Education Syllabi Pool (college-wide) | I50: GENERAL EDUCATION SYLLABI POOL (tracker item 74) — write the COURSE DESCRIPTION and the OBE SYLLABUS for 3 allocated courses, one set serving all 8 programmes: ETH-GEC Ethics; MAT-GEC Mathematics in the Modern World; BL-GEC Business Logic. 6 documents in total. Common syllabus template: 14-week trimester, 56 hours per 3-unit course, two examinations (midterm and final) plus one required monthly assessment and regular quizzes. Hand in to Chair Kent E. Garcia: descriptions 9 Oct 2026, syllabi 16 Oct 2026. Course codes are the BSA/BSAIS spellings — reconcile with your own programme's codes once Open Item 7 is closed. Not included in the BEED/BSED specialised allocation (item 79) while carrying this pool load. Records obligation on top, compulsory for all faculty: certified true copy of Transcript of Records and signed contract to HR by 30 Oct 2026 (items 12–13). | J50: #19–20, 25–26, 31–32, 37–38, 43–44, 49–50, 55–56, 61–62
A51: 47 | B51: Mequiabas, Meah | D51: Teacher Education (BEED / BSEDE / BSEDM / TEP) | E51: FT | F51: 26 | G51: 4 | H51: Curriculum & Syllabi — BEED/BSED; General Education Syllabi Pool (college-wide) | I51: GENERAL EDUCATION SYLLABI POOL (tracker item 74) — write the COURSE DESCRIPTION and the OBE SYLLABUS for 3 allocated courses, one set serving all 8 programmes: PATH-FIT 3 Dance; PATH-FIT 4 Sports; NSTP 2 Civic Welfare Training Service 2. 6 documents in total. Common syllabus template: 14-week trimester, 56 hours per 3-unit course, two examinations (midterm and final) plus one required monthly assessment and regular quizzes. Hand in to Chair Kent E. Garcia: descriptions 9 Oct 2026, syllabi 16 Oct 2026. Course codes are the BSA/BSAIS spellings — reconcile with your own programme's codes once Open Item 7 is closed. Not included in the BEED/BSED specialised allocation (item 79) while carrying this pool load. NSTP 1 is the prerequisite of NSTP 2 and the two are split between Calma and Mequiabas — agree the two syllabi between you so the sequence holds. Records obligation on top, compulsory for all faculty: certified true copy of Transcript of Records and signed contract to HR by 30 Oct 2026 (items 12–13). PROPOSED FIRST YEAR TRIMESTER LOADING — teaches ART-GEC Art Appreciation and PATH-FIT 2 (T2), PATH-FIT 3 Dance (T3). Writes the course description and the outcomes-based syllabus for each of those courses, for review by the Program Chair. | J51: #19–20, 25–26, 31–32, 37–38, 43–44, 49–50, 55–56, 61–62
A52: 48 | B52: Sta. Cruz, Ma. Patricia | D52: Teacher Education (BEED / BSEDE / BSEDM / TEP) | E52: FT | F52: 27 | G52: 3 | H52: Curriculum & Syllabi — BEED/BSED; Library Collection | I52: PROGRAMME-SPECIALISED COURSES — BEED and BSED. Write the COURSE DESCRIPTION and the OBE SYLLABUS for the BEED and BSED major courses allocated to you by Chair K. Garcia. The allocation naming your specific courses is tracked as item 79, due 25 Sep 2026. Common syllabus template: 14-week trimester, 56 hours per 3-unit course, two examinations (midterm and final) plus one required monthly assessment and regular quizzes. Hand in to your Chair: descriptions 9 Oct 2026, syllabi 16 Oct 2026. Feeds tracker items 55 and 56 (BEED) and 61 and 62 (BSED). Also a named member of the library team — owns the working papers behind items 66 to 69 with Bernardo, on top of a 27-unit teaching load. Weight your course share accordingly with the Chair. Records obligation on top, compulsory for all faculty: certified true copy of Transcript of Records and signed contract to HR by 30 Oct 2026 (items 12–13). | J52: #55–56, 61–62, 66–69 | K52: Also a member of the library team named in the project plan — library duty on top of a full teaching load.
A53: 49 | B53: Tolosa, Nenita | D53: Teacher Education (BEED / BSEDE / BSEDM / TEP) | E53: FT | F53: 24 | G53: 5 | H53: Curriculum & Syllabi — BEED/BSED; General Education Syllabi Pool (college-wide) | I53: GENERAL EDUCATION SYLLABI POOL (tracker item 74) — write the COURSE DESCRIPTION and the OBE SYLLABUS for 3 allocated courses, one set serving all 8 programmes: ART-GEC Art Appreciation; COM-GEC Purposive Communication; US-GEC Understanding the Self. 6 documents in total. Common syllabus template: 14-week trimester, 56 hours per 3-unit course, two examinations (midterm and final) plus one required monthly assessment and regular quizzes. Hand in to Chair Kent E. Garcia: descriptions 9 Oct 2026, syllabi 16 Oct 2026. Course codes are the BSA/BSAIS spellings — reconcile with your own programme's codes once Open Item 7 is closed. Not included in the BEED/BSED specialised allocation (item 79) while carrying this pool load. Records obligation on top, compulsory for all faculty: certified true copy of Transcript of Records and signed contract to HR by 30 Oct 2026 (items 12–13). PROPOSED FIRST YEAR TRIMESTER LOADING — teaches US-GEC Understanding the Self (T1). Writes the course description and the outcomes-based syllabus for each of those courses, for review by the Program Chair. | J53: #19–20, 25–26, 31–32, 37–38, 43–44, 49–50, 55–56, 61–62
A54: 50 | B54: Villamayor, Xyrelle | D54: Teacher Education (BEED / BSEDE / BSEDM / TEP) | E54: FT | F54: 27 | G54: 6 | H54: Curriculum & Syllabi — BEED/BSED | I54: PROGRAMME-SPECIALISED COURSES — BEED and BSED. Write the COURSE DESCRIPTION and the OBE SYLLABUS for the BEED and BSED major courses allocated to you by Chair K. Garcia. The allocation naming your specific courses is tracked as item 79, due 25 Sep 2026. Common syllabus template: 14-week trimester, 56 hours per 3-unit course, two examinations (midterm and final) plus one required monthly assessment and regular quizzes. Hand in to your Chair: descriptions 9 Oct 2026, syllabi 16 Oct 2026. Feeds tracker items 55 and 56 (BEED) and 61 and 62 (BSED). Records obligation on top, compulsory for all faculty: certified true copy of Transcript of Records and signed contract to HR by 30 Oct 2026 (items 12–13). PROPOSED FIRST YEAR TRIMESTER LOADING — teaches COM-GEC Purposive Communication (T2), CON-GEC The Contemporary World (T3). Writes the course description and the outcomes-based syllabus for each of those courses, for review by the Program Chair. | J54: #55–56, 61–62, #19–20, 25–26
A55: 51 | B55: Adiova, Marites | D55: Teacher Education (BEED / BSEDE / BSEDM / TEP) | E55: PT | F55: 3 | G55: 1 | H55: Not tasked — part-time | I55: Not tasked with project work (part-time). Records obligation only, and it is compulsory: submit your certified true copy of Transcript of Records and your signed appointment / contract / letter of commitment to HR Officer Dela Cruz by 30 Oct 2026 — checklist items 5.2 and 5.3, tracker items 12 and 13. | J55: — | K55: Part-time — not tasked.
A56: 52 | B56: Cabrera, Francis | D56: Teacher Education (BEED / BSEDE / BSEDM / TEP) | E56: PT | F56: 3 | G56: 1 | H56: Not tasked — part-time | I56: Not tasked with project work (part-time). Records obligation only, and it is compulsory: submit your certified true copy of Transcript of Records and your signed appointment / contract / letter of commitment to HR Officer Dela Cruz by 30 Oct 2026 — checklist items 5.2 and 5.3, tracker items 12 and 13. | J56: — | K56: Part-time — not tasked.
A57: 53 | B57: Gomez, Donna Michelle A. | D57: Teacher Education (BEED / BSEDE / BSEDM / TEP) | E57: PT | F57: 12 | G57: 1 | H57: Not tasked — part-time | I57: Not tasked with project work (part-time). Records obligation only, and it is compulsory: submit your certified true copy of Transcript of Records and your signed appointment / contract / letter of commitment to HR Officer Dela Cruz by 30 Oct 2026 — checklist items 5.2 and 5.3, tracker items 12 and 13. | J57: — | K57: Part-time — not tasked.
A58: 54 | B58: Magdaong, Jennifer | D58: Teacher Education (BEED / BSEDE / BSEDM / TEP) | E58: PT | F58: 3 | G58: 1 | H58: Not tasked — part-time | I58: Not tasked with project work (part-time). Records obligation only, and it is compulsory: submit your certified true copy of Transcript of Records and your signed appointment / contract / letter of commitment to HR Officer Dela Cruz by 30 Oct 2026 — checklist items 5.2 and 5.3, tracker items 12 and 13. | J58: — | K58: Part-time — not tasked.
A60: Unique faculty | D60: =COUNTA($B$5:$B$59)
A61: Full-time (tasked) | D61: =COUNTIF($E$5:$E$59,"FT")
A62: Part-time (not tasked) | D62: =COUNTIF($E$5:$E$59,"PT")
A63: Full-time faculty available to task (excluding the Dean, the Vice Dean and the 5 Programme Chairs; the MIS Head is on this roster as part-time) | D63: =COUNTIF($E$5:$E$59,"FT")-7
A64: Total units carried this semester | D64: =SUM($F$5:$F$59)
A65: Average units per faculty | D65: =ROUND(AVERAGE($F$5:$F$59),1)

Sheet My Outputs
A1: MY OUTPUTS — KEN GIE ANTHONY G. CRUEL, CPA, MBA
A2: Personal record of work produced on the CHED 3-Year Trimester application, in both capacities: Co-Lead of the CHED Application Task Force and Program Chair for BSA and BSAIS. Add a row each time you finish something — this is the evidence trail behind the tracker.
A4: Date | B4: Output produced | C4: Capacity | D4: Tracker item(s) it serves | E4: Status | F4: Where it lives
A5: 46261 | B5: Minutes of the Special Meeting of the Council of Program Chairs, including the drafting of Resolutions 2026-08-01 (endorsement of the 3-year trimester transition for all 8 programs), 2026-08-02 (student cohorts and institutional teach-out policy) and 2026-08-03 (mobilisation of the CHED Application Task Force) | C5: Task Force Co-Lead | D5: Item 1 | E5: For review | F5: MEETINGS OF MEETING 08.27.26.docx — circulated for signing
A6: 46262 | B6: Transmittal letter to CHED for the proposed 3-Year Trimester System | C6: Task Force Co-Lead | D6: Item 1 | E6: Done | F6: Office of the Vice Dean
A7: 46262 | B7: Four-phase project implementation plan with hard deadlines of 12 Sep, 16 Oct, 30 Oct and 13 Nov 2026, setting out direct execution and delegation for every office | C7: Task Force Co-Lead | D7: Items 1–72 | E7: Done | F7: CHED 3-Year Trimester Application.xlsx
A8: 46265 | B8: Draft 9-trimester prospectus for BSA — 191 total units across 9 terms (Year 1: 67, Year 2: 67, Year 3: 57) | C8: Program Chair, BSA | D8: Items 15, 16, 17 | E8: In progress | F8: Sample Curriculum.xlsx, sheet “BSA” — draft, not final
A9: 46265 | B9: Draft 9-trimester prospectus for BSAIS — 185 total units across 9 terms (Year 1: 67, Year 2: 67, Year 3: 51) | C9: Program Chair, BSAIS | D9: Items 21, 22, 23 | E9: In progress | F9: Sample Curriculum.xlsx, sheet “BSAIS” — draft, not final
A10: 46265 | B10: Proposed HCC academic calendar for AY 2027-2028 — three terms of 15 academic weeks each, with Christmas and Holy Week breaks absorbed, enrolment and grade-processing windows, and graduation set for 10 June 2028 | C10: Task Force Co-Lead | D10: Items 18, 24 | E10: In progress | F10: Sample Curriculum.xlsx, sheet “School Calendar”
A11: 46265 | B11: Contact-hour basis for the trimestral schedule under CMO 27 and CMO 30, series of 2017 — 14 contact hours per unit, 42 hours per 3-unit course, 2.8 hours per week over 15 weeks | C11: Program Chair, BSA & BSAIS | D11: Items 18, 24 | E11: In progress | F11: Sample Curriculum.xlsx, sheet “Sample Schedule” — weekly grid still to be built
A12: 46286 | B12: Proposed Schedule of Classes, First Year - Trimester 1 to 3, combined 1-BSA / 1-BSAIS section — 31 contact hours and 23 units per trimester, Monday to Thursday, Friday kept free | C12: Program Chair, BSA & BSAIS | D12: Items 18, 24 | E12: For review | F12: BSA & BSAIS Outputs/Sample Schedule — Word and PDF
A13: 46286 | B13: Proposed Faculty Loading, First Year - Trimester 1 to 3 — one full-time and 13 part-time faculty, units per instructor per trimester | C13: Program Chair, BSA & BSAIS | D13: Items 18, 24; supports item 11 | E13: For review | F13: BSA & BSAIS Outputs/Faculty Matrix & Loading — Word and PDF
A14: 46286 | B14: Naming convention "First Year - Trimester 1" applied to the BSA and BSAIS curricula, Sample Curriculum.xlsx, the sample schedule workbook, CHED Form 1 and 2, and both self-evaluations (builder updated) | C14: Program Chair, BSA & BSAIS | D14: Items 2, 15, 21 | E14: Done | F14: BSA & BSAIS Outputs (all subfolders); Self-Evaluation Builder
A15: 46288 | B15: Feasibility study for the conversion of the BSA to a 3-year trimester delivery — description, management viability (administrator matrix), market viability (five-year enrolment projection from 30 first-year enrollees growing 10% a year), financial viability, matters to be supplied, conclusion and recommendation; cites the Graduate Tracer Study, Batch May 2025 (28 of 30 graduates employed in their field — 93% overall, BSA 95%, BSAIS 90%) and, for BSA, the first CPALE batch (4 passers of 6) | C15: Program Chair, BSA | D15: Items 3, 4, 5, 6, 7, 8 | E15: For review | F15: BSA & BSAIS Outputs/Feasibility Study — Word and PDF
A16: 46288 | B16: Feasibility study for the conversion of the BSAIS to a 3-year trimester delivery — same structure, projected from 25 first-year enrollees growing 10% a year; cites the Graduate Tracer Study, Batch May 2025 (28 of 30 graduates employed in their field — 93% overall, BSA 95%, BSAIS 90%) and, for BSA, the first CPALE batch (4 passers of 6) | C16: Program Chair, BSAIS | D16: Items 3, 4, 5, 6, 7, 8 | E16: For review | F16: BSA & BSAIS Outputs/Feasibility Study — Word and PDF
... A23: 46321 | B23: Course teacher named on every First Year syllabus — Prepared by / Subject Instructor set from the Proposed Faculty Loading across 24 courses (J.R. Francisco: FAR, CFAS; J.R. Empay: CBME 1, BL1; D.N. Santiago: MGT1; R. Cruz: FINMGT; M. Germino: MAT-GEC, HIS-GEC; N. Tolosa: US-GEC; S.M. Calma: PATH-FIT 1; L. Ramos: NSTP 1 and 2; M. Mequiabas: ART-GEC, PATH-FIT 2 and 3; X. Villamayor: COM-GEC, CON-GEC; F. Ilag: REL-GEC, CLE 1; J. Jamlang: RIZ-GEC; Vice Dean: ECO1, IA1, CAC). Middle initials are missing for most and should be supplied before filing | C23: Program Chair, BSA & BSAIS | D23: Items 20, 26 | E23: For review | F23: BSA & BSAIS Outputs/Sample Syllabus and /Drafts for Review
A25: Outputs recorded | B25: =COUNTA($B$5:$B$23)
A26: Add new rows directly beneath row 23; the count above uses a fixed range, so widen it when you do.
